[
  {
    "folder": "layers-pointcloud-color-modulation",
    "title": "PointCloudLayer - intensity color modulation",
    "matches": false,
    "matchesCriteria": "distance < 0.15 || diff.percent < 0.15",
    "distance": 0.1875,
    "percentage": 0.6840967279926121,
    "percentageFormatted": "68.41%"
  },
  {
    "folder": "widgets-measurement-3d",
    "title": "Measurement in 3D",
    "matches": false,
    "matchesCriteria": "distance < 0.15 || diff.percent < 0.15",
    "distance": 0.1875,
    "percentage": 0.6540154946166991,
    "percentageFormatted": "65.4%"
  },
  {
    "folder": "visualization-sm-classbreaks",
    "title": "Generate a class breaks visualization",
    "matches": true,
    "matchesCriteria": "distance < 0.15 || diff.percent < 0.15",
    "distance": 0.125,
    "percentage": 0.45454857136537324,
    "percentageFormatted": "45.45%"
  },
  {
    "folder": "widgets-editor-basic",
    "title": "Edit features with the Editor widget",
    "matches": false,
    "matchesCriteria": "distance < 0.15 || diff.percent < 0.15",
    "distance": 0.171875,
    "percentage": 0.3862528133070113,
    "percentageFormatted": "38.63%"
  },
  {
    "folder": "layers-custom-dynamiclayer",
    "title": "Custom DynamicLayer",
    "matches": true,
    "matchesCriteria": "distance < 0.15 || diff.percent < 0.15",
    "distance": 0.015625,
    "percentage": 0.31003942777197147,
    "percentageFormatted": "31%"
  },
  {
    "folder": "widgets-editor-3d",
    "title": "Edit features in 3D with the Editor widget",
    "matches": true,
    "matchesCriteria": "distance < 0.15 || diff.percent < 0.15",
    "distance": 0.109375,
    "percentage": 0.2898400216769798,
    "percentageFormatted": "28.98%"
  },
  {
    "folder": "custom-lv-masking",
    "title": "Masking effect using a custom layer view",
    "matches": false,
    "matchesCriteria": "distance < 0.15 || diff.percent < 0.15",
    "distance": 0.21875,
    "percentage": 0.28742237484585564,
    "percentageFormatted": "28.74%"
  },
  {
    "folder": "layers-medialayer-video",
    "title": "MediaLayer with video",
    "matches": false,
    "matchesCriteria": "distance < 0.15 || diff.percent < 0.15",
    "distance": 0.1875,
    "percentage": 0.2209735839457633,
    "percentageFormatted": "22.1%"
  },
  {
    "folder": "intro-layers",
    "title": "Intro to layers",
    "matches": true,
    "matchesCriteria": "distance < 0.15 || diff.percent < 0.15",
    "distance": 0.015625,
    "percentage": 0.15941759706254804,
    "percentageFormatted": "15.94%"
  },
  {
    "folder": "layers-pointcloud",
    "title": "PointCloudLayer - toggle renderers",
    "matches": true,
    "matchesCriteria": "distance < 0.15 || diff.percent < 0.15",
    "distance": 0.140625,
    "percentage": 0.12456521618916483,
    "percentageFormatted": "12.46%"
  },
  {
    "folder": "scene-blendmode",
    "title": "Blend modes in 3D",
    "matches": true,
    "matchesCriteria": "distance < 0.15 || diff.percent < 0.15",
    "distance": 0.0625,
    "percentage": 0.1048590719819506,
    "percentageFormatted": "10.49%"
  },
  {
    "folder": "layers-scenelayer-feature-masking",
    "title": "Filter SceneLayer with FeatureFilter",
    "matches": true,
    "matchesCriteria": "distance < 0.15 || diff.percent < 0.15",
    "distance": 0.03125,
    "percentage": 0.09432804127473914,
    "percentageFormatted": "9.433%"
  },
  {
    "folder": "visualization-heatmap",
    "title": "Visualize points with a heatmap",
    "matches": true,
    "matchesCriteria": "distance < 0.15 || diff.percent < 0.15",
    "distance": 0.09375,
    "percentage": 0.08982675005668088,
    "percentageFormatted": "8.983%"
  },
  {
    "folder": "visualization-line-patterns",
    "title": "3D hiking map with line patterns",
    "matches": true,
    "matchesCriteria": "distance < 0.15 || diff.percent < 0.15",
    "distance": 0.03125,
    "percentage": 0.05537915360241544,
    "percentageFormatted": "5.538%"
  },
  {
    "folder": "scene-easy-navigate",
    "title": "Update the camera in a 3D view",
    "matches": true,
    "matchesCriteria": "distance < 0.15 || diff.percent < 0.15",
    "distance": 0.046875,
    "percentage": 0.05477750681553001,
    "percentageFormatted": "5.478%"
  },
  {
    "folder": "scene-toggle-elevation",
    "title": "Toggle ground elevation",
    "matches": true,
    "matchesCriteria": "distance < 0.15 || diff.percent < 0.15",
    "distance": 0,
    "percentage": 0.0545917041313448,
    "percentageFormatted": "5.459%"
  },
  {
    "folder": "visualization-point-styles",
    "title": "Point styles for cities",
    "matches": true,
    "matchesCriteria": "distance < 0.15 || diff.percent < 0.15",
    "distance": 0.015625,
    "percentage": 0.053492371583249,
    "percentageFormatted": "5.349%"
  },
  {
    "folder": "labels-basic",
    "title": "Add labels to a FeatureLayer",
    "matches": true,
    "matchesCriteria": "distance < 0.15 || diff.percent < 0.15",
    "distance": 0.015625,
    "percentage": 0.051541443399304346,
    "percentageFormatted": "5.154%"
  },
  {
    "folder": "visualization-webstylesymbol",
    "title": "Visualize features with realistic WebStyleSymbols",
    "matches": true,
    "matchesCriteria": "distance < 0.15 || diff.percent < 0.15",
    "distance": 0.015625,
    "percentage": 0.04984820584283084,
    "percentageFormatted": "4.985%"
  },
  {
    "folder": "overview-map",
    "title": "Overview map",
    "matches": true,
    "matchesCriteria": "distance < 0.15 || diff.percent < 0.15",
    "distance": 0.046875,
    "percentage": 0.04970774786133369,
    "percentageFormatted": "4.971%"
  },
  {
    "folder": "widgets-timeslider",
    "title": "TimeSlider widget",
    "matches": true,
    "matchesCriteria": "distance < 0.15 || diff.percent < 0.15",
    "distance": 0.09375,
    "percentage": 0.0493073873156489,
    "percentageFormatted": "4.931%"
  },
  {
    "folder": "visualization-trees-realistic",
    "title": "Thematic visualization with realistic 3D symbols",
    "matches": true,
    "matchesCriteria": "distance < 0.15 || diff.percent < 0.15",
    "distance": 0,
    "percentage": 0.04733433976453934,
    "percentageFormatted": "4.733%"
  },
  {
    "folder": "geometry-mesh-primitives",
    "title": "Working with 3D mesh primitives",
    "matches": true,
    "matchesCriteria": "distance < 0.15 || diff.percent < 0.15",
    "distance": 0.03125,
    "percentage": 0.04642855167913646,
    "percentageFormatted": "4.643%"
  },
  {
    "folder": "geoprocessing-viewshed",
    "title": "Geoprocessing - viewshed analysis",
    "matches": true,
    "matchesCriteria": "distance < 0.15 || diff.percent < 0.15",
    "distance": 0.015625,
    "percentage": 0.04360501446053629,
    "percentageFormatted": "4.361%"
  },
  {
    "folder": "sketch-3d",
    "title": "Sketch in 3D",
    "matches": true,
    "matchesCriteria": "distance < 0.15 || diff.percent < 0.15",
    "distance": 0.015625,
    "percentage": 0.04298788411663542,
    "percentageFormatted": "4.299%"
  },
  {
    "folder": "webscene-slides",
    "title": "Web scene - slides",
    "matches": true,
    "matchesCriteria": "distance < 0.15 || diff.percent < 0.15",
    "distance": 0.046875,
    "percentage": 0.042547708710053804,
    "percentageFormatted": "4.255%"
  },
  {
    "folder": "featurereduction-cluster-symbol",
    "title": "Override cluster symbol",
    "matches": true,
    "matchesCriteria": "distance < 0.15 || diff.percent < 0.15",
    "distance": 0.015625,
    "percentage": 0.042360800057510355,
    "percentageFormatted": "4.236%"
  },
  {
    "folder": "layers-custom-elevation-thematic",
    "title": "Custom ElevationLayer - Thematic data as elevation",
    "matches": true,
    "matchesCriteria": "distance < 0.15 || diff.percent < 0.15",
    "distance": 0.015625,
    "percentage": 0.040382222664609564,
    "percentageFormatted": "4.038%"
  },
  {
    "folder": "featurereduction-cluster",
    "title": "Point clustering - basic configuration",
    "matches": true,
    "matchesCriteria": "distance < 0.15 || diff.percent < 0.15",
    "distance": 0.015625,
    "percentage": 0.039991815834148986,
    "percentageFormatted": "3.999%"
  },
  {
    "folder": "editing-applyedits",
    "title": "Update FeatureLayer using applyEdits()",
    "matches": true,
    "matchesCriteria": "distance < 0.15 || diff.percent < 0.15",
    "distance": 0.0625,
    "percentage": 0.03984140413742763,
    "percentageFormatted": "3.984%"
  },
  {
    "folder": "visualization-multivariate-2d",
    "title": "Thematic multivariate visualization (2D)",
    "matches": true,
    "matchesCriteria": "distance < 0.15 || diff.percent < 0.15",
    "distance": 0,
    "percentage": 0.037615089832279895,
    "percentageFormatted": "3.762%"
  },
  {
    "folder": "visualization-label-callout",
    "title": "Using callout lines with labels",
    "matches": true,
    "matchesCriteria": "distance < 0.15 || diff.percent < 0.15",
    "distance": 0.015625,
    "percentage": 0.03728661722988105,
    "percentageFormatted": "3.729%"
  },
  {
    "folder": "layers-streamlayer",
    "title": "StreamLayer",
    "matches": true,
    "matchesCriteria": "distance < 0.15 || diff.percent < 0.15",
    "distance": 0.015625,
    "percentage": 0.035880931446551315,
    "percentageFormatted": "3.588%"
  },
  {
    "folder": "layers-geojson",
    "title": "GeoJSONLayer",
    "matches": true,
    "matchesCriteria": "distance < 0.15 || diff.percent < 0.15",
    "distance": 0,
    "percentage": 0.0342706415169462,
    "percentageFormatted": "3.427%"
  },
  {
    "folder": "basemap-custom",
    "title": "Custom Basemap",
    "matches": true,
    "matchesCriteria": "distance < 0.15 || diff.percent < 0.15",
    "distance": 0,
    "percentage": 0.03384152579394704,
    "percentageFormatted": "3.384%"
  },
  {
    "folder": "featurelayerview-query-aggregate",
    "title": "Aggregate spatial statistics",
    "matches": true,
    "matchesCriteria": "distance < 0.15 || diff.percent < 0.15",
    "distance": 0,
    "percentage": 0.0319669094267213,
    "percentageFormatted": "3.197%"
  },
  {
    "folder": "widgets-editor-configurable",
    "title": "Editor widget with configurations",
    "matches": true,
    "matchesCriteria": "distance < 0.15 || diff.percent < 0.15",
    "distance": 0,
    "percentage": 0.025387503663520185,
    "percentageFormatted": "2.539%"
  },
  {
    "folder": "layers-medialayer-images",
    "title": "MediaLayer with images",
    "matches": true,
    "matchesCriteria": "distance < 0.15 || diff.percent < 0.15",
    "distance": 0,
    "percentage": 0.023851313613917506,
    "percentageFormatted": "2.385%"
  },
  {
    "folder": "layers-voxel-variable",
    "title": "VoxelLayer variable and render mode",
    "matches": true,
    "matchesCriteria": "distance < 0.15 || diff.percent < 0.15",
    "distance": 0,
    "percentage": 0.01953803701676095,
    "percentageFormatted": "1.954%"
  },
  {
    "folder": "layers-pointcloud-portal",
    "title": "Intro to PointCloudLayer",
    "matches": true,
    "matchesCriteria": "distance < 0.15 || diff.percent < 0.15",
    "distance": 0.015625,
    "percentage": 0.01945840729496729,
    "percentageFormatted": "1.946%"
  },
  {
    "folder": "layers-scenelayer-texture",
    "title": "Realistic buildings with SceneLayer",
    "matches": true,
    "matchesCriteria": "distance < 0.15 || diff.percent < 0.15",
    "distance": 0.015625,
    "percentage": 0.01943075808601116,
    "percentageFormatted": "1.943%"
  },
  {
    "folder": "geometry-mesh-elevation",
    "title": "Low poly terrain using mesh geometry",
    "matches": true,
    "matchesCriteria": "distance < 0.15 || diff.percent < 0.15",
    "distance": 0.015625,
    "percentage": 0.019337856743918556,
    "percentageFormatted": "1.934%"
  },
  {
    "folder": "featurelayerview-query-geometry",
    "title": "FeatureLayerView - query statistics by geometry",
    "matches": true,
    "matchesCriteria": "distance < 0.15 || diff.percent < 0.15",
    "distance": 0.078125,
    "percentage": 0.018771600944496977,
    "percentageFormatted": "1.877%"
  },
  {
    "folder": "visualization-unique-value-groups",
    "title": "Unique value groups with headings",
    "matches": true,
    "matchesCriteria": "distance < 0.15 || diff.percent < 0.15",
    "distance": 0,
    "percentage": 0.018454188025680586,
    "percentageFormatted": "1.845%"
  },
  {
    "folder": "widgets-histogramrangeslider",
    "title": "HistogramRangeSlider",
    "matches": true,
    "matchesCriteria": "distance < 0.15 || diff.percent < 0.15",
    "distance": 0,
    "percentage": 0.0179365948340218,
    "percentageFormatted": "1.794%"
  },
  {
    "folder": "satellites-3d",
    "title": "Satellites in 3D view",
    "matches": true,
    "matchesCriteria": "distance < 0.15 || diff.percent < 0.15",
    "distance": 0,
    "percentage": 0.017902309814916195,
    "percentageFormatted": "1.79%"
  },
  {
    "folder": "webscene-basic",
    "title": "Load a basic web scene",
    "matches": true,
    "matchesCriteria": "distance < 0.15 || diff.percent < 0.15",
    "distance": 0.046875,
    "percentage": 0.016723347545026735,
    "percentageFormatted": "1.672%"
  },
  {
    "folder": "scene-external-renderer",
    "title": "Extend the SceneView WebGL engine",
    "matches": true,
    "matchesCriteria": "distance < 0.15 || diff.percent < 0.15",
    "distance": 0,
    "percentage": 0.016508789683527154,
    "percentageFormatted": "1.651%"
  },
  {
    "folder": "featurelayerview-query-distance",
    "title": "Query statistics client-side by distance",
    "matches": true,
    "matchesCriteria": "distance < 0.15 || diff.percent < 0.15",
    "distance": 0,
    "percentage": 0.01581977139634035,
    "percentageFormatted": "1.582%"
  },
  {
    "folder": "scene-weather",
    "title": "Weather visualization",
    "matches": true,
    "matchesCriteria": "distance < 0.15 || diff.percent < 0.15",
    "distance": 0.03125,
    "percentage": 0.013944049060756372,
    "percentageFormatted": "1.394%"
  },
  {
    "folder": "view-breakpoints-css",
    "title": "Responsive apps using CSS",
    "matches": true,
    "matchesCriteria": "distance < 0.15 || diff.percent < 0.15",
    "distance": 0.015625,
    "percentage": 0.013344614210587436,
    "percentageFormatted": "1.334%"
  },
  {
    "folder": "custom-gl-animated-lines",
    "title": "Animated lines with WebGL",
    "matches": true,
    "matchesCriteria": "distance < 0.15 || diff.percent < 0.15",
    "distance": 0,
    "percentage": 0.011655800527546906,
    "percentageFormatted": "1.166%"
  },
  {
    "folder": "featurereduction-cluster-filter-slider",
    "title": "Point clustering - advanced configuration",
    "matches": true,
    "matchesCriteria": "distance < 0.15 || diff.percent < 0.15",
    "distance": 0.03125,
    "percentage": 0.011207883342457573,
    "percentageFormatted": "1.121%"
  },
  {
    "folder": "widgets-featureform-async",
    "title": "Editing with calculated field expressions",
    "matches": true,
    "matchesCriteria": "distance < 0.15 || diff.percent < 0.15",
    "distance": 0,
    "percentage": 0.01113378346245514,
    "percentageFormatted": "1.113%"
  },
  {
    "folder": "sceneview-memory",
    "title": "SceneView memory resources",
    "matches": true,
    "matchesCriteria": "distance < 0.15 || diff.percent < 0.15",
    "distance": 0.015625,
    "percentage": 0.01083185410065418,
    "percentageFormatted": "1.083%"
  },
  {
    "folder": "widgets-daylight",
    "title": "Daylight widget",
    "matches": true,
    "matchesCriteria": "distance < 0.15 || diff.percent < 0.15",
    "distance": 0.0625,
    "percentage": 0.010188180516155432,
    "percentageFormatted": "1.019%"
  },
  {
    "folder": "visualization-sm-dotdensity",
    "title": "Generate a dot density visualization",
    "matches": true,
    "matchesCriteria": "distance < 0.15 || diff.percent < 0.15",
    "distance": 0,
    "percentage": 0.010035556882717586,
    "percentageFormatted": "1.004%"
  },
  {
    "folder": "featurereduction-cluster-visualvariables",
    "title": "Point clustering with visual variables",
    "matches": true,
    "matchesCriteria": "distance < 0.15 || diff.percent < 0.15",
    "distance": 0,
    "percentage": 0.009678329103004363,
    "percentageFormatted": "0.9678%"
  },
  {
    "folder": "widgets-legend",
    "title": "Legend widget",
    "matches": true,
    "matchesCriteria": "distance < 0.15 || diff.percent < 0.15",
    "distance": 0,
    "percentage": 0.009467089146579516,
    "percentageFormatted": "0.9467%"
  },
  {
    "folder": "widgets-layerlist",
    "title": "LayerList widget",
    "matches": true,
    "matchesCriteria": "distance < 0.15 || diff.percent < 0.15",
    "distance": 0,
    "percentage": 0.009443863811056366,
    "percentageFormatted": "0.9444%"
  },
  {
    "folder": "widgets-shadow-cast",
    "title": "Shadow cast",
    "matches": true,
    "matchesCriteria": "distance < 0.15 || diff.percent < 0.15",
    "distance": 0,
    "percentage": 0.009139722512538917,
    "percentageFormatted": "0.914%"
  },
  {
    "folder": "elevation-query",
    "title": "Query Elevation (lines)",
    "matches": true,
    "matchesCriteria": "distance < 0.15 || diff.percent < 0.15",
    "distance": 0,
    "percentage": 0.008832263308946731,
    "percentageFormatted": "0.8832%"
  },
  {
    "folder": "popuptemplate-browse-related-records",
    "title": "Browse related records in a popup",
    "matches": true,
    "matchesCriteria": "distance < 0.15 || diff.percent < 0.15",
    "distance": 0,
    "percentage": 0.008806826036707089,
    "percentageFormatted": "0.8807%"
  },
  {
    "folder": "elevation-query-points",
    "title": "Query Elevation (points)",
    "matches": true,
    "matchesCriteria": "distance < 0.15 || diff.percent < 0.15",
    "distance": 0.015625,
    "percentage": 0.00864535465640328,
    "percentageFormatted": "0.8645%"
  },
  {
    "folder": "layers-scenelayer-filter-query",
    "title": "SceneLayer filter and query",
    "matches": true,
    "matchesCriteria": "distance < 0.15 || diff.percent < 0.15",
    "distance": 0,
    "percentage": 0.008560195092818395,
    "percentageFormatted": "0.856%"
  },
  {
    "folder": "time-layer",
    "title": "Time-based layer",
    "matches": true,
    "matchesCriteria": "distance < 0.15 || diff.percent < 0.15",
    "distance": 0,
    "percentage": 0.00836222675669249,
    "percentageFormatted": "0.8362%"
  },
  {
    "folder": "watch-for-changes-reactiveutils",
    "title": "Property Changes with ReactiveUtils",
    "matches": true,
    "matchesCriteria": "distance < 0.15 || diff.percent < 0.15",
    "distance": 0.015625,
    "percentage": 0.007995045261755061,
    "percentageFormatted": "0.7995%"
  },
  {
    "folder": "webscene-save",
    "title": "Save a web scene",
    "matches": true,
    "matchesCriteria": "distance < 0.15 || diff.percent < 0.15",
    "distance": 0,
    "percentage": 0.007943064748917534,
    "percentageFormatted": "0.7943%"
  },
  {
    "folder": "layers-scenelayer-edges",
    "title": "Add edges to a SceneLayer",
    "matches": true,
    "matchesCriteria": "distance < 0.15 || diff.percent < 0.15",
    "distance": 0.03125,
    "percentage": 0.007714129298760763,
    "percentageFormatted": "0.7714%"
  },
  {
    "folder": "featureeffect-multiple-effects",
    "title": "Highlight areas intersecting borough boundaries",
    "matches": true,
    "matchesCriteria": "distance < 0.15 || diff.percent < 0.15",
    "distance": 0,
    "percentage": 0.007564823570397651,
    "percentageFormatted": "0.7565%"
  },
  {
    "folder": "analysis-objects",
    "title": "Analysis object",
    "matches": true,
    "matchesCriteria": "distance < 0.15 || diff.percent < 0.15",
    "distance": 0,
    "percentage": 0.007432107367408219,
    "percentageFormatted": "0.7432%"
  },
  {
    "folder": "watch-for-changes",
    "title": "Watch for changes",
    "matches": true,
    "matchesCriteria": "distance < 0.15 || diff.percent < 0.15",
    "distance": 0,
    "percentage": 0.007397822348302615,
    "percentageFormatted": "0.7398%"
  },
  {
    "folder": "visualization-realistic-water",
    "title": "Realistic water visualization in 3D",
    "matches": true,
    "matchesCriteria": "distance < 0.15 || diff.percent < 0.15",
    "distance": 0,
    "percentage": 0.006933315637839601,
    "percentageFormatted": "0.6933%"
  },
  {
    "folder": "building-scene-layer-filter",
    "title": "Filter BuildingSceneLayer with BuildingExplorer",
    "matches": true,
    "matchesCriteria": "distance < 0.15 || diff.percent < 0.15",
    "distance": 0.015625,
    "percentage": 0.0066479758014123215,
    "percentageFormatted": "0.6648%"
  },
  {
    "folder": "featurereduction-cluster-filter",
    "title": "Point clustering - generate suggested configuration",
    "matches": true,
    "matchesCriteria": "distance < 0.15 || diff.percent < 0.15",
    "distance": 0,
    "percentage": 0.0064068746993148525,
    "percentageFormatted": "0.6407%"
  },
  {
    "folder": "labels-multiple-classes",
    "title": "Add multiple label classes to a layer",
    "matches": true,
    "matchesCriteria": "distance < 0.15 || diff.percent < 0.15",
    "distance": 0.015625,
    "percentage": 0.005889281507656066,
    "percentageFormatted": "0.5889%"
  },
  {
    "folder": "custom-gl-visuals",
    "title": "Custom WebGL layer view",
    "matches": true,
    "matchesCriteria": "distance < 0.15 || diff.percent < 0.15",
    "distance": 0,
    "percentage": 0.005735551905859973,
    "percentageFormatted": "0.5736%"
  },
  {
    "folder": "sketch-viewmodel-styler",
    "title": "SketchViewModel Styler",
    "matches": true,
    "matchesCriteria": "distance < 0.15 || diff.percent < 0.15",
    "distance": 0,
    "percentage": 0.005233442271216621,
    "percentageFormatted": "0.5233%"
  },
  {
    "folder": "visualization-heatmap-scene",
    "title": "Visualize points in a scene with a heatmap",
    "matches": true,
    "matchesCriteria": "distance < 0.15 || diff.percent < 0.15",
    "distance": 0.03125,
    "percentage": 0.005165978201363659,
    "percentageFormatted": "0.5166%"
  },
  {
    "folder": "widgets-line-of-sight",
    "title": "Line of sight widget",
    "matches": true,
    "matchesCriteria": "distance < 0.15 || diff.percent < 0.15",
    "distance": 0,
    "percentage": 0.005115103656884377,
    "percentageFormatted": "0.5115%"
  },
  {
    "folder": "import-gltf",
    "title": "Import glTF 3D Models",
    "matches": true,
    "matchesCriteria": "distance < 0.15 || diff.percent < 0.15",
    "distance": 0,
    "percentage": 0.005085242511211755,
    "percentageFormatted": "0.5085%"
  },
  {
    "folder": "popup-editaction",
    "title": "Popup with edit action",
    "matches": true,
    "matchesCriteria": "distance < 0.15 || diff.percent < 0.15",
    "distance": 0,
    "percentage": 0.0048574130294132285,
    "percentageFormatted": "0.4857%"
  },
  {
    "folder": "layers-custom-elevation-exaggerated",
    "title": "Custom ElevationLayer - Exaggerating elevation",
    "matches": true,
    "matchesCriteria": "distance < 0.15 || diff.percent < 0.15",
    "distance": 0.015625,
    "percentage": 0.004655020819854344,
    "percentageFormatted": "0.4655%"
  },
  {
    "folder": "visualization-buildings-3d",
    "title": "Extrude building footprints based on real world heights",
    "matches": true,
    "matchesCriteria": "distance < 0.15 || diff.percent < 0.15",
    "distance": 0.015625,
    "percentage": 0.004651702914779609,
    "percentageFormatted": "0.4652%"
  },
  {
    "folder": "highlight-scenelayer",
    "title": "Highlight SceneLayer",
    "matches": true,
    "matchesCriteria": "distance < 0.15 || diff.percent < 0.15",
    "distance": 0,
    "percentage": 0.004612994022241024,
    "percentageFormatted": "0.4613%"
  },
  {
    "folder": "layers-imagery-afrenderer-blending",
    "title": "FlowRenderer with effects and blending",
    "matches": true,
    "matchesCriteria": "distance < 0.15 || diff.percent < 0.15",
    "distance": 0,
    "percentage": 0.004603040307016817,
    "percentageFormatted": "0.4603%"
  },
  {
    "folder": "graphics-basic-3d",
    "title": "Add Graphics to a SceneView",
    "matches": true,
    "matchesCriteria": "distance < 0.15 || diff.percent < 0.15",
    "distance": 0,
    "percentage": 0.004598616433583835,
    "percentageFormatted": "0.4599%"
  },
  {
    "folder": "custom-lv-deckgl",
    "title": "Build a custom layer view using deck.gl",
    "matches": true,
    "matchesCriteria": "distance < 0.15 || diff.percent < 0.15",
    "distance": 0.015625,
    "percentage": 0.004324336280739008,
    "percentageFormatted": "0.4324%"
  },
  {
    "folder": "layers-imagery-afrenderer",
    "title": "FlowRenderer with visual variables",
    "matches": true,
    "matchesCriteria": "distance < 0.15 || diff.percent < 0.15",
    "distance": 0,
    "percentage": 0.003960472690876314,
    "percentageFormatted": "0.396%"
  },
  {
    "folder": "widgets-featuretable-editing",
    "title": "FeatureTable with editing enabled",
    "matches": true,
    "matchesCriteria": "distance < 0.15 || diff.percent < 0.15",
    "distance": 0,
    "percentage": 0.0034849062968308475,
    "percentageFormatted": "0.3485%"
  },
  {
    "folder": "layers-kml",
    "title": "KMLLayer",
    "matches": true,
    "matchesCriteria": "distance < 0.15 || diff.percent < 0.15",
    "distance": 0,
    "percentage": 0.003345554283691944,
    "percentageFormatted": "0.3346%"
  },
  {
    "folder": "scene-shadow",
    "title": "SceneView - shadow and lighting settings",
    "matches": true,
    "matchesCriteria": "distance < 0.15 || diff.percent < 0.15",
    "distance": 0,
    "percentage": 0.003273666340406001,
    "percentageFormatted": "0.3274%"
  },
  {
    "folder": "layers-scenelayer",
    "title": "Intro to SceneLayer",
    "matches": true,
    "matchesCriteria": "distance < 0.15 || diff.percent < 0.15",
    "distance": 0.015625,
    "percentage": 0.0032438051947333785,
    "percentageFormatted": "0.3244%"
  },
  {
    "folder": "scene-elevationinfo",
    "title": "Elevation options",
    "matches": true,
    "matchesCriteria": "distance < 0.15 || diff.percent < 0.15",
    "distance": 0,
    "percentage": 0.0029839026305457403,
    "percentageFormatted": "0.2984%"
  },
  {
    "folder": "visualization-sm-color-mesh",
    "title": "Generate continuous color visualization for 3D buildings",
    "matches": true,
    "matchesCriteria": "distance < 0.15 || diff.percent < 0.15",
    "distance": 0,
    "percentage": 0.0028876833833784013,
    "percentageFormatted": "0.2888%"
  },
  {
    "folder": "sceneview-screenshot",
    "title": "Take a screenshot of a SceneView",
    "matches": true,
    "matchesCriteria": "distance < 0.15 || diff.percent < 0.15",
    "distance": 0,
    "percentage": 0.0028843654783036656,
    "percentageFormatted": "0.2884%"
  },
  {
    "folder": "layers-routelayer",
    "title": "Intro to RouteLayer",
    "matches": true,
    "matchesCriteria": "distance < 0.15 || diff.percent < 0.15",
    "distance": 0,
    "percentage": 0.0027450134651647615,
    "percentageFormatted": "0.2745%"
  },
  {
    "folder": "popuptemplate-arcade-expression-content",
    "title": "Create popup charts from Arcade expressions",
    "matches": true,
    "matchesCriteria": "distance < 0.15 || diff.percent < 0.15",
    "distance": 0.015625,
    "percentage": 0.0027317418448658186,
    "percentageFormatted": "0.2732%"
  },
  {
    "folder": "visualization-trees-2d",
    "title": "Scale feature sizes based on real world sizes (2D)",
    "matches": true,
    "matchesCriteria": "distance < 0.15 || diff.percent < 0.15",
    "distance": 0,
    "percentage": 0.0027040926359096864,
    "percentageFormatted": "0.2704%"
  },
  {
    "folder": "ge-geodesicbuffer",
    "title": "GeometryEngine - geodesic buffers",
    "matches": true,
    "matchesCriteria": "distance < 0.15 || diff.percent < 0.15",
    "distance": 0.015625,
    "percentage": 0.002653218091430404,
    "percentageFormatted": "0.2653%"
  },
  {
    "folder": "scene-elevationlayer",
    "title": "ElevationLayer",
    "matches": true,
    "matchesCriteria": "distance < 0.15 || diff.percent < 0.15",
    "distance": 0.015625,
    "percentage": 0.002612297262175329,
    "percentageFormatted": "0.2612%"
  },
  {
    "folder": "featurelayer-query",
    "title": "Query top features from a FeatureLayer",
    "matches": true,
    "matchesCriteria": "distance < 0.15 || diff.percent < 0.15",
    "distance": 0.0625,
    "percentage": 0.0025614227176960465,
    "percentageFormatted": "0.2561%"
  },
  {
    "folder": "building-scene-layer-slice",
    "title": "BuildingSceneLayer with Slice widget",
    "matches": true,
    "matchesCriteria": "distance < 0.15 || diff.percent < 0.15",
    "distance": 0,
    "percentage": 0.0025171839833662358,
    "percentageFormatted": "0.2517%"
  },
  {
    "folder": "cim-lines-and-polygons",
    "title": "CIMSymbol lines and polygons",
    "matches": true,
    "matchesCriteria": "distance < 0.15 || diff.percent < 0.15",
    "distance": 0,
    "percentage": 0.0024696273439616893,
    "percentageFormatted": "0.247%"
  },
  {
    "folder": "widgets-editor-3d-scenelayer",
    "title": "SceneLayer attribute editing",
    "matches": true,
    "matchesCriteria": "distance < 0.15 || diff.percent < 0.15",
    "distance": 0,
    "percentage": 0.002462991533812218,
    "percentageFormatted": "0.2463%"
  },
  {
    "folder": "layers-scenelayerview-query",
    "title": "Query client-side 3D extents",
    "matches": true,
    "matchesCriteria": "distance < 0.15 || diff.percent < 0.15",
    "distance": 0,
    "percentage": 0.002460779597095727,
    "percentageFormatted": "0.2461%"
  },
  {
    "folder": "featurelayer-queryextent",
    "title": "Zoom to extent of all features",
    "matches": true,
    "matchesCriteria": "distance < 0.15 || diff.percent < 0.15",
    "distance": 0.03125,
    "percentage": 0.002263917229328069,
    "percentageFormatted": "0.2264%"
  },
  {
    "folder": "widgets-search-customsource",
    "title": "Search widget with custom source",
    "matches": true,
    "matchesCriteria": "distance < 0.15 || diff.percent < 0.15",
    "distance": 0,
    "percentage": 0.0022340560836554466,
    "percentageFormatted": "0.2234%"
  },
  {
    "folder": "visualization-polygon-patterns",
    "title": "Urban visualizations with polygon patterns",
    "matches": true,
    "matchesCriteria": "distance < 0.15 || diff.percent < 0.15",
    "distance": 0,
    "percentage": 0.0022097247797740506,
    "percentageFormatted": "0.221%"
  },
  {
    "folder": "visualization-dot-density",
    "title": "Dot density",
    "matches": true,
    "matchesCriteria": "distance < 0.15 || diff.percent < 0.15",
    "distance": 0,
    "percentage": 0.002203088969624579,
    "percentageFormatted": "0.2203%"
  },
  {
    "folder": "layers-hosted-imagerytilelayer-landcover",
    "title": "Hosted Land Cover ImageryTileLayer",
    "matches": true,
    "matchesCriteria": "distance < 0.15 || diff.percent < 0.15",
    "distance": 0,
    "percentage": 0.002005120633498676,
    "percentageFormatted": "0.2005%"
  },
  {
    "folder": "popuptemplate-arcade-groupby",
    "title": "Summarize intersecting points in a popup",
    "matches": true,
    "matchesCriteria": "distance < 0.15 || diff.percent < 0.15",
    "distance": 0.015625,
    "percentage": 0.0018524970000608283,
    "percentageFormatted": "0.1852%"
  },
  {
    "folder": "widgets-feature",
    "title": "Feature Widget",
    "matches": true,
    "matchesCriteria": "distance < 0.15 || diff.percent < 0.15",
    "distance": 0,
    "percentage": 0.001618031708112831,
    "percentageFormatted": "0.1618%"
  },
  {
    "folder": "layers-scenelayerview-query-stats",
    "title": "SceneLayerView - query statistics by geometry",
    "matches": true,
    "matchesCriteria": "distance < 0.15 || diff.percent < 0.15",
    "distance": 0,
    "percentage": 0.0015218124609454923,
    "percentageFormatted": "0.1522%"
  },
  {
    "folder": "visualization-path-3d",
    "title": "Path visualization in 3D",
    "matches": true,
    "matchesCriteria": "distance < 0.15 || diff.percent < 0.15",
    "distance": 0.015625,
    "percentage": 0.0013470694603427396,
    "percentageFormatted": "0.1347%"
  },
  {
    "folder": "sketch-update-validation",
    "title": "Sketch update validation",
    "matches": true,
    "matchesCriteria": "distance < 0.15 || diff.percent < 0.15",
    "distance": 0,
    "percentage": 0.001336009776760287,
    "percentageFormatted": "0.1336%"
  },
  {
    "folder": "route",
    "title": "Route",
    "matches": true,
    "matchesCriteria": "distance < 0.15 || diff.percent < 0.15",
    "distance": 0,
    "percentage": 0.0013304799349690606,
    "percentageFormatted": "0.133%"
  },
  {
    "folder": "highlight-point-features",
    "title": "Highlight point features",
    "matches": true,
    "matchesCriteria": "distance < 0.15 || diff.percent < 0.15",
    "distance": 0,
    "percentage": 0.0012420024663094388,
    "percentageFormatted": "0.1242%"
  },
  {
    "folder": "editing-featureform-fieldvisibility",
    "title": "Advanced Attribute Editing",
    "matches": true,
    "matchesCriteria": "distance < 0.15 || diff.percent < 0.15",
    "distance": 0,
    "percentage": 0.0012088234155620808,
    "percentageFormatted": "0.1209%"
  },
  {
    "folder": "layers-dynamicdatalayer-raster",
    "title": "MapImageLayer - raster data source",
    "matches": true,
    "matchesCriteria": "distance < 0.15 || diff.percent < 0.15",
    "distance": 0,
    "percentage": 0.0011623727445157794,
    "percentageFormatted": "0.1162%"
  },
  {
    "folder": "layers-featurelayer-labeling-3d",
    "title": "Label features using Arcade expressions",
    "matches": true,
    "matchesCriteria": "distance < 0.15 || diff.percent < 0.15",
    "distance": 0.015625,
    "percentage": 0.0010772131809308936,
    "percentageFormatted": "0.1077%"
  },
  {
    "folder": "layers-dimension",
    "title": "Length dimensioning",
    "matches": true,
    "matchesCriteria": "distance < 0.15 || diff.percent < 0.15",
    "distance": 0.015625,
    "percentage": 0.0009666163451063666,
    "percentageFormatted": "0.09666%"
  },
  {
    "folder": "visualization-heatmap-scale",
    "title": "Create a scale-dependent visualization",
    "matches": true,
    "matchesCriteria": "distance < 0.15 || diff.percent < 0.15",
    "distance": 0,
    "percentage": 0.0009644044083898759,
    "percentageFormatted": "0.09644%"
  },
  {
    "folder": "widgets-directions",
    "title": "Directions widget",
    "matches": true,
    "matchesCriteria": "distance < 0.15 || diff.percent < 0.15",
    "distance": 0,
    "percentage": 0.0009334372943590084,
    "percentageFormatted": "0.09334%"
  },
  {
    "folder": "popup-domnode",
    "title": "Popup with DOM node",
    "matches": true,
    "matchesCriteria": "distance < 0.15 || diff.percent < 0.15",
    "distance": 0.015625,
    "percentage": 0.0008748209713720091,
    "percentageFormatted": "0.08748%"
  },
  {
    "folder": "layers-pointcloud-filters",
    "title": "Filter points in a PointCloudLayer",
    "matches": true,
    "matchesCriteria": "distance < 0.15 || diff.percent < 0.15",
    "distance": 0,
    "percentage": 0.000817310616743255,
    "percentageFormatted": "0.08173%"
  },
  {
    "folder": "scene-local",
    "title": "Create a local scene",
    "matches": true,
    "matchesCriteria": "distance < 0.15 || diff.percent < 0.15",
    "distance": 0,
    "percentage": 0.0007233033062924069,
    "percentageFormatted": "0.07233%"
  },
  {
    "folder": "widgets-coordinateconversion-custom",
    "title": "CoordinateConversion widget - Custom Formats",
    "matches": true,
    "matchesCriteria": "distance < 0.15 || diff.percent < 0.15",
    "distance": 0,
    "percentage": 0.0006326139009162948,
    "percentageFormatted": "0.06326%"
  },
  {
    "folder": "visualization-sm-relationship",
    "title": "Generate a relationship visualization",
    "matches": true,
    "matchesCriteria": "distance < 0.15 || diff.percent < 0.15",
    "distance": 0,
    "percentage": 0.0005728916095710502,
    "percentageFormatted": "0.05729%"
  },
  {
    "folder": "layers-feature-sort-order",
    "title": "Configure feature sort order",
    "matches": true,
    "matchesCriteria": "distance < 0.15 || diff.percent < 0.15",
    "distance": 0,
    "percentage": 0.0005430304638984278,
    "percentageFormatted": "0.0543%"
  },
  {
    "folder": "intro-popup",
    "title": "Intro to popups",
    "matches": true,
    "matchesCriteria": "distance < 0.15 || diff.percent < 0.15",
    "distance": 0,
    "percentage": 0.0005275469068829941,
    "percentageFormatted": "0.05275%"
  },
  {
    "folder": "layers-scenelayer-color-mix-mode",
    "title": "Coloring options for textured buildings",
    "matches": true,
    "matchesCriteria": "distance < 0.15 || diff.percent < 0.15",
    "distance": 0,
    "percentage": 0.0005186991600170319,
    "percentageFormatted": "0.05187%"
  },
  {
    "folder": "layers-custom-tilelayer",
    "title": "Custom TileLayer",
    "matches": true,
    "matchesCriteria": "distance < 0.15 || diff.percent < 0.15",
    "distance": 0.03125,
    "percentage": 0.0004534470268805609,
    "percentageFormatted": "0.04534%"
  },
  {
    "folder": "webstylesymbol-2d",
    "title": "WebStyleSymbol (2D)",
    "matches": true,
    "matchesCriteria": "distance < 0.15 || diff.percent < 0.15",
    "distance": 0,
    "percentage": 0.00044238734329810823,
    "percentageFormatted": "0.04424%"
  },
  {
    "folder": "webscene-slide-tour",
    "title": "Web scene - slide tour",
    "matches": true,
    "matchesCriteria": "distance < 0.15 || diff.percent < 0.15",
    "distance": 0,
    "percentage": 0.00043575153314863663,
    "percentageFormatted": "0.04358%"
  },
  {
    "folder": "layers-pointcloud-size-density",
    "title": "PointCloudLayer - change point size and density",
    "matches": true,
    "matchesCriteria": "distance < 0.15 || diff.percent < 0.15",
    "distance": 0,
    "percentage": 0.0004324336280739008,
    "percentageFormatted": "0.04324%"
  },
  {
    "folder": "widgets-featuretable-map",
    "title": "FeatureTable with a map",
    "matches": true,
    "matchesCriteria": "distance < 0.15 || diff.percent < 0.15",
    "distance": 0,
    "percentage": 0.0004069963558342596,
    "percentageFormatted": "0.0407%"
  },
  {
    "folder": "widgets-floorfilter",
    "title": "FloorFilter widget",
    "matches": true,
    "matchesCriteria": "distance < 0.15 || diff.percent < 0.15",
    "distance": 0,
    "percentage": 0.0004069963558342596,
    "percentageFormatted": "0.0407%"
  },
  {
    "folder": "widgets-elevation-profile",
    "title": "ElevationProfile Widget",
    "matches": true,
    "matchesCriteria": "distance < 0.15 || diff.percent < 0.15",
    "distance": 0,
    "percentage": 0.0004025724824012785,
    "percentageFormatted": "0.04026%"
  },
  {
    "folder": "layers-scenelayer-scene-masking",
    "title": "Filter SceneLayer with SceneFilter",
    "matches": true,
    "matchesCriteria": "distance < 0.15 || diff.percent < 0.15",
    "distance": 0,
    "percentage": 0.0003771352101616373,
    "percentageFormatted": "0.03771%"
  },
  {
    "folder": "arcade-execute-chart",
    "title": "Execute Arcade for a custom chart",
    "matches": true,
    "matchesCriteria": "distance < 0.15 || diff.percent < 0.15",
    "distance": 0,
    "percentage": 0.0003030353301592041,
    "percentageFormatted": "0.0303%"
  },
  {
    "folder": "visualization-dictionary",
    "title": "Visualize data with dictionary renderer",
    "matches": true,
    "matchesCriteria": "distance < 0.15 || diff.percent < 0.15",
    "distance": 0,
    "percentage": 0.0003030353301592041,
    "percentageFormatted": "0.0303%"
  },
  {
    "folder": "widgets-legend-update",
    "title": "Update legend text",
    "matches": true,
    "matchesCriteria": "distance < 0.15 || diff.percent < 0.15",
    "distance": 0,
    "percentage": 0.00028312789971078926,
    "percentageFormatted": "0.02831%"
  },
  {
    "folder": "mars",
    "title": "Visualize data on Mars",
    "matches": true,
    "matchesCriteria": "distance < 0.15 || diff.percent < 0.15",
    "distance": 0,
    "percentage": 0.00025547869075465753,
    "percentageFormatted": "0.02555%"
  },
  {
    "folder": "sceneview-hittest",
    "title": "SceneView - hitTest",
    "matches": true,
    "matchesCriteria": "distance < 0.15 || diff.percent < 0.15",
    "distance": 0,
    "percentage": 0.00023778319702273318,
    "percentageFormatted": "0.02378%"
  },
  {
    "folder": "sketch-geometries",
    "title": "Sketch widget",
    "matches": true,
    "matchesCriteria": "distance < 0.15 || diff.percent < 0.15",
    "distance": 0,
    "percentage": 0.00023667722866448792,
    "percentageFormatted": "0.02367%"
  },
  {
    "folder": "layers-wms",
    "title": "WMSLayer",
    "matches": true,
    "matchesCriteria": "distance < 0.15 || diff.percent < 0.15",
    "distance": 0.015625,
    "percentage": 0.00022782948179852575,
    "percentageFormatted": "0.02278%"
  },
  {
    "folder": "analysis-area-measurement",
    "title": "Area measurement analysis object",
    "matches": true,
    "matchesCriteria": "distance < 0.15 || diff.percent < 0.15",
    "distance": 0.015625,
    "percentage": 0.00021566382985782777,
    "percentageFormatted": "0.02157%"
  },
  {
    "folder": "featurereduction-cluster-pie-charts",
    "title": "Clusters as pie charts",
    "matches": true,
    "matchesCriteria": "distance < 0.15 || diff.percent < 0.15",
    "distance": 0,
    "percentage": 0.00020018027284239397,
    "percentageFormatted": "0.02002%"
  },
  {
    "folder": "cim-marker-placement",
    "title": "Adjust marker placement in polygon symbols",
    "matches": true,
    "matchesCriteria": "distance < 0.15 || diff.percent < 0.15",
    "distance": 0,
    "percentage": 0.0001990743044841487,
    "percentageFormatted": "0.01991%"
  },
  {
    "folder": "visualization-vv-color-animate",
    "title": "Animate color visual variable",
    "matches": true,
    "matchesCriteria": "distance < 0.15 || diff.percent < 0.15",
    "distance": 0,
    "percentage": 0.00018912058925994128,
    "percentageFormatted": "0.01891%"
  },
  {
    "folder": "widgets-untrace",
    "title": "UtilityNetworkTrace widget",
    "matches": true,
    "matchesCriteria": "distance < 0.15 || diff.percent < 0.15",
    "distance": 0,
    "percentage": 0.00016810719045328112,
    "percentageFormatted": "0.01681%"
  },
  {
    "folder": "visualization-sm-location-scale",
    "title": "Vary point sizes by scale",
    "matches": true,
    "matchesCriteria": "distance < 0.15 || diff.percent < 0.15",
    "distance": 0,
    "percentage": 0.00016147138030380952,
    "percentageFormatted": "0.01615%"
  },
  {
    "folder": "widgets-swipe-scroll",
    "title": "Swipe Widget with Scroll",
    "matches": true,
    "matchesCriteria": "distance < 0.15 || diff.percent < 0.15",
    "distance": 0,
    "percentage": 0.00015262363343784735,
    "percentageFormatted": "0.01526%"
  },
  {
    "folder": "visualization-update-data",
    "title": "Update a renderer's attribute",
    "matches": true,
    "matchesCriteria": "distance < 0.15 || diff.percent < 0.15",
    "distance": 0,
    "percentage": 0.0001271863611982061,
    "percentageFormatted": "0.01272%"
  },
  {
    "folder": "layers-mapimagelayer-definitionexpression",
    "title": "MapImageLayer - Set definition expressions on sublayers",
    "matches": true,
    "matchesCriteria": "distance < 0.15 || diff.percent < 0.15",
    "distance": 0.015625,
    "percentage": 0.00012165651940697976,
    "percentageFormatted": "0.01217%"
  },
  {
    "folder": "widgets-track",
    "title": "Track widget simulation",
    "matches": true,
    "matchesCriteria": "distance < 0.15 || diff.percent < 0.15",
    "distance": 0,
    "percentage": 0.00011170280418277233,
    "percentageFormatted": "0.01117%"
  },
  {
    "folder": "featurereduction-binning-filter",
    "title": "Binning - Filter by category",
    "matches": true,
    "matchesCriteria": "distance < 0.15 || diff.percent < 0.15",
    "distance": 0,
    "percentage": 0.00009290134209260274,
    "percentageFormatted": "0.00929%"
  },
  {
    "folder": "widgets-expand",
    "title": "Expand widget",
    "matches": true,
    "matchesCriteria": "distance < 0.15 || diff.percent < 0.15",
    "distance": 0,
    "percentage": 0.00007852375343541422,
    "percentageFormatted": "0.007852%"
  },
  {
    "folder": "featurereduction-cluster-popup-chart",
    "title": "Popup charts for point clusters",
    "matches": true,
    "matchesCriteria": "distance < 0.15 || diff.percent < 0.15",
    "distance": 0,
    "percentage": 0.00007409988000243313,
    "percentageFormatted": "0.00741%"
  },
  {
    "folder": "featurereduction-cluster-popup-filter",
    "title": "Point clustering - filter popup features",
    "matches": true,
    "matchesCriteria": "distance < 0.15 || diff.percent < 0.15",
    "distance": 0,
    "percentage": 0.00007409988000243313,
    "percentageFormatted": "0.00741%"
  },
  {
    "folder": "featurereduction-cluster-query",
    "title": "Point clustering - query clusters",
    "matches": true,
    "matchesCriteria": "distance < 0.15 || diff.percent < 0.15",
    "distance": 0,
    "percentage": 0.00007409988000243313,
    "percentageFormatted": "0.00741%"
  },
  {
    "folder": "query",
    "title": "Query",
    "matches": true,
    "matchesCriteria": "distance < 0.15 || diff.percent < 0.15",
    "distance": 0,
    "percentage": 0.00007188794328594259,
    "percentageFormatted": "0.007189%"
  },
  {
    "folder": "scene-webgl-support",
    "title": "Detect WebGL support",
    "matches": true,
    "matchesCriteria": "distance < 0.15 || diff.percent < 0.15",
    "distance": 0.015625,
    "percentage": 0.00007078197492769731,
    "percentageFormatted": "0.007078%"
  },
  {
    "folder": "visualization-vv-opacity-animate",
    "title": "Animate layer view effect",
    "matches": true,
    "matchesCriteria": "distance < 0.15 || diff.percent < 0.15",
    "distance": 0,
    "percentage": 0.00006857003821120677,
    "percentageFormatted": "0.006857%"
  },
  {
    "folder": "layers-csv",
    "title": "Intro to CSVLayer",
    "matches": true,
    "matchesCriteria": "distance < 0.15 || diff.percent < 0.15",
    "distance": 0.015625,
    "percentage": 0.00006525213313647097,
    "percentageFormatted": "0.006525%"
  },
  {
    "folder": "visualization-sm-uni-colorsize",
    "title": "Generate univariate continuous size and color visualization in 3D",
    "matches": true,
    "matchesCriteria": "distance < 0.15 || diff.percent < 0.15",
    "distance": 0,
    "percentage": 0.00006525213313647097,
    "percentageFormatted": "0.006525%"
  },
  {
    "folder": "widgets-basemapgallery",
    "title": "BasemapGallery widget",
    "matches": true,
    "matchesCriteria": "distance < 0.15 || diff.percent < 0.15",
    "distance": 0,
    "percentage": 0.00005419244955401826,
    "percentageFormatted": "0.005419%"
  },
  {
    "folder": "intro-blendmode-layer",
    "title": "Intro to layer blending",
    "matches": true,
    "matchesCriteria": "distance < 0.15 || diff.percent < 0.15",
    "distance": 0,
    "percentage": 0.00005087454447928245,
    "percentageFormatted": "0.005087%"
  },
  {
    "folder": "event-explorer",
    "title": "Event explorer / watch properties",
    "matches": true,
    "matchesCriteria": "distance < 0.15 || diff.percent < 0.15",
    "distance": 0,
    "percentage": 0.00004976857612103718,
    "percentageFormatted": "0.004977%"
  },
  {
    "folder": "visualization-vv-opacity",
    "title": "Data-driven opacity",
    "matches": true,
    "matchesCriteria": "distance < 0.15 || diff.percent < 0.15",
    "distance": 0,
    "percentage": 0.00004976857612103718,
    "percentageFormatted": "0.004977%"
  },
  {
    "folder": "widgets-feature-multiplelayers",
    "title": "Feature widget - Query graphics from multiple layerViews",
    "matches": true,
    "matchesCriteria": "distance < 0.15 || diff.percent < 0.15",
    "distance": 0,
    "percentage": 0.00004976857612103718,
    "percentageFormatted": "0.004977%"
  },
  {
    "folder": "layers-mapimagelayer",
    "title": "Intro to MapImageLayer",
    "matches": true,
    "matchesCriteria": "distance < 0.15 || diff.percent < 0.15",
    "distance": 0,
    "percentage": 0.000047556639404546633,
    "percentageFormatted": "0.004756%"
  },
  {
    "folder": "visualization-classbreaks",
    "title": "Visualize data with class breaks",
    "matches": true,
    "matchesCriteria": "distance < 0.15 || diff.percent < 0.15",
    "distance": 0,
    "percentage": 0.00004645067104630137,
    "percentageFormatted": "0.004645%"
  },
  {
    "folder": "views-synchronize",
    "title": "Synchronize MapView and SceneView",
    "matches": true,
    "matchesCriteria": "distance < 0.15 || diff.percent < 0.15",
    "distance": 0,
    "percentage": 0.0000376029241803392,
    "percentageFormatted": "0.00376%"
  },
  {
    "folder": "intro-sceneview",
    "title": "Intro to SceneView - Create a 3D map",
    "matches": true,
    "matchesCriteria": "distance < 0.15 || diff.percent < 0.15",
    "distance": 0,
    "percentage": 0.000034285019105603385,
    "percentageFormatted": "0.003429%"
  },
  {
    "folder": "symbols-points-3d",
    "title": "Flat vs. volumetric 3D symbol layers",
    "matches": true,
    "matchesCriteria": "distance < 0.15 || diff.percent < 0.15",
    "distance": 0,
    "percentage": 0.000034285019105603385,
    "percentageFormatted": "0.003429%"
  },
  {
    "folder": "visualization-vv-extrusion",
    "title": "Data-driven extrusion",
    "matches": true,
    "matchesCriteria": "distance < 0.15 || diff.percent < 0.15",
    "distance": 0,
    "percentage": 0.000029861145672622305,
    "percentageFormatted": "0.002986%"
  },
  {
    "folder": "layers-imagery-popup",
    "title": "ImageryLayer - server side raster function",
    "matches": true,
    "matchesCriteria": "distance < 0.15 || diff.percent < 0.15",
    "distance": 0,
    "percentage": 0.000026543240597886493,
    "percentageFormatted": "0.002654%"
  },
  {
    "folder": "sceneview-background",
    "title": "Custom background for SceneView",
    "matches": true,
    "matchesCriteria": "distance < 0.15 || diff.percent < 0.15",
    "distance": 0,
    "percentage": 0.000026543240597886493,
    "percentageFormatted": "0.002654%"
  },
  {
    "folder": "visualization-line-markers",
    "title": "Line markers and label placement",
    "matches": true,
    "matchesCriteria": "distance < 0.15 || diff.percent < 0.15",
    "distance": 0,
    "percentage": 0.000025437272239641224,
    "percentageFormatted": "0.002544%"
  },
  {
    "folder": "layers-imagerytilelayer-cog",
    "title": "ImageryTileLayer with COG",
    "matches": true,
    "matchesCriteria": "distance < 0.15 || diff.percent < 0.15",
    "distance": 0,
    "percentage": 0.00002101339880666014,
    "percentageFormatted": "0.002101%"
  },
  {
    "folder": "visualization-multivariate-3d",
    "title": "Thematic multivariate visualization (3D)",
    "matches": true,
    "matchesCriteria": "distance < 0.15 || diff.percent < 0.15",
    "distance": 0,
    "percentage": 0.00002101339880666014,
    "percentageFormatted": "0.002101%"
  },
  {
    "folder": "layers-dynamicmaplayer",
    "title": "MapImageLayer - create dynamic map layers",
    "matches": true,
    "matchesCriteria": "distance < 0.15 || diff.percent < 0.15",
    "distance": 0,
    "percentage": 0.0000188014620901696,
    "percentageFormatted": "0.00188%"
  },
  {
    "folder": "layers-voxel",
    "title": "Intro to Voxel Layer",
    "matches": true,
    "matchesCriteria": "distance < 0.15 || diff.percent < 0.15",
    "distance": 0,
    "percentage": 0.00001658952537367906,
    "percentageFormatted": "0.001659%"
  },
  {
    "folder": "layers-webtile-3d",
    "title": "WebTileLayer",
    "matches": true,
    "matchesCriteria": "distance < 0.15 || diff.percent < 0.15",
    "distance": 0,
    "percentage": 0.00001658952537367906,
    "percentageFormatted": "0.001659%"
  },
  {
    "folder": "webstylesymbol-proportional-2d",
    "title": "Proportionally-sized WebStyleSymbols (2D)",
    "matches": true,
    "matchesCriteria": "distance < 0.15 || diff.percent < 0.15",
    "distance": 0,
    "percentage": 0.000011059683582452706,
    "percentageFormatted": "0.001106%"
  },
  {
    "folder": "sceneview-underground",
    "title": "Underground navigation in global mode",
    "matches": true,
    "matchesCriteria": "distance < 0.15 || diff.percent < 0.15",
    "distance": 0,
    "percentage": 0.000009953715224207436,
    "percentageFormatted": "0.0009954%"
  },
  {
    "folder": "cim-symbols",
    "title": "CIMSymbol",
    "matches": true,
    "matchesCriteria": "distance < 0.15 || diff.percent < 0.15",
    "distance": 0,
    "percentage": 0.000008847746865962164,
    "percentageFormatted": "0.0008848%"
  },
  {
    "folder": "layers-vectortilelayer-json",
    "title": "VectorTileLayer - update style layers",
    "matches": true,
    "matchesCriteria": "distance < 0.15 || diff.percent < 0.15",
    "distance": 0,
    "percentage": 0.000008847746865962164,
    "percentageFormatted": "0.0008848%"
  },
  {
    "folder": "widgets-compass-2d",
    "title": "Compass widget",
    "matches": true,
    "matchesCriteria": "distance < 0.15 || diff.percent < 0.15",
    "distance": 0,
    "percentage": 0.000008847746865962164,
    "percentageFormatted": "0.0008848%"
  },
  {
    "folder": "widgets-track-basic",
    "title": "Track current location",
    "matches": true,
    "matchesCriteria": "distance < 0.15 || diff.percent < 0.15",
    "distance": 0,
    "percentage": 0.000008847746865962164,
    "percentageFormatted": "0.0008848%"
  },
  {
    "folder": "layers-portal",
    "title": "Create a layer from a portal item",
    "matches": true,
    "matchesCriteria": "distance < 0.15 || diff.percent < 0.15",
    "distance": 0,
    "percentage": 0.000007741778507716894,
    "percentageFormatted": "0.0007742%"
  },
  {
    "folder": "featurereduction-binning",
    "title": "Binning - basic configuration",
    "matches": true,
    "matchesCriteria": "distance < 0.15 || diff.percent < 0.15",
    "distance": 0,
    "percentage": 0.000005529841791226353,
    "percentageFormatted": "0.000553%"
  },
  {
    "folder": "identify",
    "title": "Identify",
    "matches": true,
    "matchesCriteria": "distance < 0.15 || diff.percent < 0.15",
    "distance": 0,
    "percentage": 0.000005529841791226353,
    "percentageFormatted": "0.000553%"
  },
  {
    "folder": "layers-vectortilelayer-style",
    "title": "VectorTileLayer - update style",
    "matches": true,
    "matchesCriteria": "distance < 0.15 || diff.percent < 0.15",
    "distance": 0,
    "percentage": 0.000005529841791226353,
    "percentageFormatted": "0.000553%"
  },
  {
    "folder": "view-breakpoints",
    "title": "Responsive widgets",
    "matches": true,
    "matchesCriteria": "distance < 0.15 || diff.percent < 0.15",
    "distance": 0,
    "percentage": 0.000005529841791226353,
    "percentageFormatted": "0.000553%"
  },
  {
    "folder": "widgets-search-3d",
    "title": "Search Widget",
    "matches": true,
    "matchesCriteria": "distance < 0.15 || diff.percent < 0.15",
    "distance": 0,
    "percentage": 0.000004423873432981082,
    "percentageFormatted": "0.0004424%"
  },
  {
    "folder": "cim-line-arrows",
    "title": "Arrows along a line",
    "matches": true,
    "matchesCriteria": "distance < 0.15 || diff.percent < 0.15",
    "distance": 0,
    "percentage": 0.0000033179050747358116,
    "percentageFormatted": "0.0003318%"
  },
  {
    "folder": "featurereduction-cluster-aggregate-fields",
    "title": "Clustering with aggregate fields",
    "matches": true,
    "matchesCriteria": "distance < 0.15 || diff.percent < 0.15",
    "distance": 0,
    "percentage": 0.0000033179050747358116,
    "percentageFormatted": "0.0003318%"
  },
  {
    "folder": "scene-goto",
    "title": "SceneView - goTo()",
    "matches": true,
    "matchesCriteria": "distance < 0.15 || diff.percent < 0.15",
    "distance": 0,
    "percentage": 0.0000033179050747358116,
    "percentageFormatted": "0.0003318%"
  },
  {
    "folder": "widgets-home",
    "title": "Home button",
    "matches": true,
    "matchesCriteria": "distance < 0.15 || diff.percent < 0.15",
    "distance": 0.015625,
    "percentage": 0.000002211936716490541,
    "percentageFormatted": "0.0002212%"
  },
  {
    "folder": "layers-georss",
    "title": "GeoRSSLayer",
    "matches": true,
    "matchesCriteria": "distance < 0.15 || diff.percent < 0.15",
    "distance": 0,
    "percentage": 0.000002211936716490541,
    "percentageFormatted": "0.0002212%"
  },
  {
    "folder": "layers-osm-3d",
    "title": "OpenStreetMapLayer",
    "matches": true,
    "matchesCriteria": "distance < 0.15 || diff.percent < 0.15",
    "distance": 0,
    "percentage": 0.000002211936716490541,
    "percentageFormatted": "0.0002212%"
  },
  {
    "folder": "popup-multipleelements",
    "title": "Multiple popup elements",
    "matches": true,
    "matchesCriteria": "distance < 0.15 || diff.percent < 0.15",
    "distance": 0,
    "percentage": 0.000002211936716490541,
    "percentageFormatted": "0.0002212%"
  },
  {
    "folder": "layers-scenelayer-points",
    "title": "Scene Layer with point geometries",
    "matches": true,
    "matchesCriteria": "distance < 0.15 || diff.percent < 0.15",
    "distance": 0.046875,
    "percentage": 0.0000011059683582452705,
    "percentageFormatted": "0.0001106%"
  },
  {
    "folder": "featureeffect-layers-histogram",
    "title": "Apply featureEffect to a FeatureLayer",
    "matches": true,
    "matchesCriteria": "distance < 0.15 || diff.percent < 0.15",
    "distance": 0,
    "percentage": 0.0000011059683582452705,
    "percentageFormatted": "0.0001106%"
  },
  {
    "folder": "layers-imagerytilelayer",
    "title": "Intro to ImageryTileLayer",
    "matches": true,
    "matchesCriteria": "distance < 0.15 || diff.percent < 0.15",
    "distance": 0,
    "percentage": 0.0000011059683582452705,
    "percentageFormatted": "0.0001106%"
  },
  {
    "folder": "layers-integratedmeshlayer-modification",
    "title": "IntegratedMeshLayer modification",
    "matches": true,
    "matchesCriteria": "distance < 0.15 || diff.percent < 0.15",
    "distance": 0,
    "percentage": 0.0000011059683582452705,
    "percentageFormatted": "0.0001106%"
  },
  {
    "folder": "layers-ogcfeaturelayer",
    "title": "OGCFeatureLayer",
    "matches": true,
    "matchesCriteria": "distance < 0.15 || diff.percent < 0.15",
    "distance": 0,
    "percentage": 0.0000011059683582452705,
    "percentageFormatted": "0.0001106%"
  },
  {
    "folder": "popup-custom-action",
    "title": "Custom popup actions per feature attribute",
    "matches": true,
    "matchesCriteria": "distance < 0.15 || diff.percent < 0.15",
    "distance": 0,
    "percentage": 0.0000011059683582452705,
    "percentageFormatted": "0.0001106%"
  },
  {
    "folder": "simple-ui",
    "title": "Using the view's UI",
    "matches": true,
    "matchesCriteria": "distance < 0.15 || diff.percent < 0.15",
    "distance": 0,
    "percentage": 0.0000011059683582452705,
    "percentageFormatted": "0.0001106%"
  },
  {
    "folder": "visualization-heatmap-static",
    "title": "Create a static heatmap",
    "matches": true,
    "matchesCriteria": "distance < 0.15 || diff.percent < 0.15",
    "distance": 0,
    "percentage": 0.0000011059683582452705,
    "percentageFormatted": "0.0001106%"
  },
  {
    "folder": "view-disable-zoom",
    "title": "Disable mouse-wheel and single-touch navigation",
    "matches": true,
    "matchesCriteria": "distance < 0.15 || diff.percent < 0.15",
    "distance": 0.34375,
    "percentage": 0,
    "percentageFormatted": "0%"
  },
  {
    "folder": "geoprocessing-hotspot",
    "title": "Geoprocessing - hotspot analysis",
    "matches": true,
    "matchesCriteria": "distance < 0.15 || diff.percent < 0.15",
    "distance": 0.015625,
    "percentage": 0,
    "percentageFormatted": "0%"
  },
  {
    "folder": "animation-layer-visibility",
    "title": "Animate layer visibility",
    "matches": true,
    "matchesCriteria": "distance < 0.15 || diff.percent < 0.15",
    "distance": 0,
    "percentage": 0,
    "percentageFormatted": "0%"
  },
  {
    "folder": "basemaps-portal",
    "title": "Basemaps with different projections",
    "matches": true,
    "matchesCriteria": "distance < 0.15 || diff.percent < 0.15",
    "distance": 0,
    "percentage": 0,
    "percentageFormatted": "0%"
  },
  {
    "folder": "blendmode-darkening",
    "title": "Multiply blendMode",
    "matches": true,
    "matchesCriteria": "distance < 0.15 || diff.percent < 0.15",
    "distance": 0,
    "percentage": 0,
    "percentageFormatted": "0%"
  },
  {
    "folder": "blendmode-grouplayer",
    "title": "Composite blending",
    "matches": true,
    "matchesCriteria": "distance < 0.15 || diff.percent < 0.15",
    "distance": 0,
    "percentage": 0,
    "percentageFormatted": "0%"
  },
  {
    "folder": "blendmode-multiple-layers",
    "title": "Highlight feature with effects and blending",
    "matches": true,
    "matchesCriteria": "distance < 0.15 || diff.percent < 0.15",
    "distance": 0,
    "percentage": 0,
    "percentageFormatted": "0%"
  },
  {
    "folder": "cim-primitive-overrides",
    "title": "Wurman dots",
    "matches": true,
    "matchesCriteria": "distance < 0.15 || diff.percent < 0.15",
    "distance": 0,
    "percentage": 0,
    "percentageFormatted": "0%"
  },
  {
    "folder": "client-projection",
    "title": "Client-side projection",
    "matches": true,
    "matchesCriteria": "distance < 0.15 || diff.percent < 0.15",
    "distance": 0,
    "percentage": 0,
    "percentageFormatted": "0%"
  },
  {
    "folder": "custom-gl-tessellation-helpers",
    "title": "Tessellation helpers for custom WebGL layer views",
    "matches": true,
    "matchesCriteria": "distance < 0.15 || diff.percent < 0.15",
    "distance": 0,
    "percentage": 0,
    "percentageFormatted": "0%"
  },
  {
    "folder": "custom-gl-tiles",
    "title": "Tiling support for custom WebGL layer views",
    "matches": true,
    "matchesCriteria": "distance < 0.15 || diff.percent < 0.15",
    "distance": 0,
    "percentage": 0,
    "percentageFormatted": "0%"
  },
  {
    "folder": "draw-line",
    "title": "Draw polyline",
    "matches": true,
    "matchesCriteria": "distance < 0.15 || diff.percent < 0.15",
    "distance": 0,
    "percentage": 0,
    "percentageFormatted": "0%"
  },
  {
    "folder": "editing-groupedfeatureform",
    "title": "Update Feature Attributes",
    "matches": true,
    "matchesCriteria": "distance < 0.15 || diff.percent < 0.15",
    "distance": 0,
    "percentage": 0,
    "percentageFormatted": "0%"
  },
  {
    "folder": "effect-blur-shadow",
    "title": "Highlight a country with an effect",
    "matches": true,
    "matchesCriteria": "distance < 0.15 || diff.percent < 0.15",
    "distance": 0,
    "percentage": 0,
    "percentageFormatted": "0%"
  },
  {
    "folder": "featureeffect-drop-shadow",
    "title": "Apply drop-shadow effects to layerview",
    "matches": true,
    "matchesCriteria": "distance < 0.15 || diff.percent < 0.15",
    "distance": 0,
    "percentage": 0,
    "percentageFormatted": "0%"
  },
  {
    "folder": "featureeffect-geometry",
    "title": "Apply effects to features",
    "matches": true,
    "matchesCriteria": "distance < 0.15 || diff.percent < 0.15",
    "distance": 0,
    "percentage": 0,
    "percentageFormatted": "0%"
  },
  {
    "folder": "featurefilter-attributes",
    "title": "Filter features by attribute",
    "matches": true,
    "matchesCriteria": "distance < 0.15 || diff.percent < 0.15",
    "distance": 0,
    "percentage": 0,
    "percentageFormatted": "0%"
  },
  {
    "folder": "featurelayer-query-basic",
    "title": "Basic Querying in FeatureLayer",
    "matches": true,
    "matchesCriteria": "distance < 0.15 || diff.percent < 0.15",
    "distance": 0,
    "percentage": 0,
    "percentageFormatted": "0%"
  },
  {
    "folder": "featurelayer-query-pagination",
    "title": "Query features with pagination",
    "matches": true,
    "matchesCriteria": "distance < 0.15 || diff.percent < 0.15",
    "distance": 0,
    "percentage": 0,
    "percentageFormatted": "0%"
  },
  {
    "folder": "featurelayerview-query",
    "title": "Query features from a FeatureLayerView",
    "matches": true,
    "matchesCriteria": "distance < 0.15 || diff.percent < 0.15",
    "distance": 0,
    "percentage": 0,
    "percentageFormatted": "0%"
  },
  {
    "folder": "featurelayerview-query-stats",
    "title": "Query statistics client-side",
    "matches": true,
    "matchesCriteria": "distance < 0.15 || diff.percent < 0.15",
    "distance": 0,
    "percentage": 0,
    "percentageFormatted": "0%"
  },
  {
    "folder": "featurereduction-binning-aggregate-fields",
    "title": "Binning with aggregate fields",
    "matches": true,
    "matchesCriteria": "distance < 0.15 || diff.percent < 0.15",
    "distance": 0,
    "percentage": 0,
    "percentageFormatted": "0%"
  },
  {
    "folder": "featurereduction-binning-arcade-summary",
    "title": "Summarize binned data using Arcade",
    "matches": true,
    "matchesCriteria": "distance < 0.15 || diff.percent < 0.15",
    "distance": 0,
    "percentage": 0,
    "percentageFormatted": "0%"
  },
  {
    "folder": "featurereduction-cluster-renderer-sum",
    "title": "Cluster size based on the sum of a field",
    "matches": true,
    "matchesCriteria": "distance < 0.15 || diff.percent < 0.15",
    "distance": 0,
    "percentage": 0,
    "percentageFormatted": "0%"
  },
  {
    "folder": "find",
    "title": "Find",
    "matches": true,
    "matchesCriteria": "distance < 0.15 || diff.percent < 0.15",
    "distance": 0,
    "percentage": 0,
    "percentageFormatted": "0%"
  },
  {
    "folder": "highlight-features-by-geometry",
    "title": "Select features by rectangle",
    "matches": true,
    "matchesCriteria": "distance < 0.15 || diff.percent < 0.15",
    "distance": 0,
    "percentage": 0,
    "percentageFormatted": "0%"
  },
  {
    "folder": "highlightoptions-layerviews",
    "title": "Highlight options for layer views",
    "matches": true,
    "matchesCriteria": "distance < 0.15 || diff.percent < 0.15",
    "distance": 0,
    "percentage": 0,
    "percentageFormatted": "0%"
  },
  {
    "folder": "identity-oauth-basic",
    "title": "Access ArcGIS Online items using OAuth 2.0",
    "matches": true,
    "matchesCriteria": "distance < 0.15 || diff.percent < 0.15",
    "distance": 0,
    "percentage": 0,
    "percentageFormatted": "0%"
  },
  {
    "folder": "intro-effect-layer",
    "title": "Intro to layer effect",
    "matches": true,
    "matchesCriteria": "distance < 0.15 || diff.percent < 0.15",
    "distance": 0,
    "percentage": 0,
    "percentageFormatted": "0%"
  },
  {
    "folder": "intro-graphics",
    "title": "Intro to graphics",
    "matches": true,
    "matchesCriteria": "distance < 0.15 || diff.percent < 0.15",
    "distance": 0,
    "percentage": 0,
    "percentageFormatted": "0%"
  },
  {
    "folder": "intro-mapview",
    "title": "Intro to MapView - Create a 2D map",
    "matches": true,
    "matchesCriteria": "distance < 0.15 || diff.percent < 0.15",
    "distance": 0,
    "percentage": 0,
    "percentageFormatted": "0%"
  },
  {
    "folder": "intro-popuptemplate",
    "title": "Intro to PopupTemplate",
    "matches": true,
    "matchesCriteria": "distance < 0.15 || diff.percent < 0.15",
    "distance": 0,
    "percentage": 0,
    "percentageFormatted": "0%"
  },
  {
    "folder": "intro-widgets",
    "title": "Intro to widgets using BasemapToggle",
    "matches": true,
    "matchesCriteria": "distance < 0.15 || diff.percent < 0.15",
    "distance": 0,
    "percentage": 0,
    "percentageFormatted": "0%"
  },
  {
    "folder": "labels-multiline",
    "title": "Multi-line labels",
    "matches": true,
    "matchesCriteria": "distance < 0.15 || diff.percent < 0.15",
    "distance": 0,
    "percentage": 0,
    "percentageFormatted": "0%"
  },
  {
    "folder": "layers-csv-projection",
    "title": "CSVLayer - Project points on the fly",
    "matches": true,
    "matchesCriteria": "distance < 0.15 || diff.percent < 0.15",
    "distance": 0,
    "percentage": 0,
    "percentageFormatted": "0%"
  },
  {
    "folder": "layers-custom-blendlayer",
    "title": "Custom BlendLayer",
    "matches": true,
    "matchesCriteria": "distance < 0.15 || diff.percent < 0.15",
    "distance": 0,
    "percentage": 0,
    "percentageFormatted": "0%"
  },
  {
    "folder": "layers-custom-lerc-2d",
    "title": "Custom LERC Layer",
    "matches": true,
    "matchesCriteria": "distance < 0.15 || diff.percent < 0.15",
    "distance": 0,
    "percentage": 0,
    "percentageFormatted": "0%"
  },
  {
    "folder": "layers-dynamicdatalayer-query-table",
    "title": "MapImageLayer - dynamic data layer with query table",
    "matches": true,
    "matchesCriteria": "distance < 0.15 || diff.percent < 0.15",
    "distance": 0,
    "percentage": 0,
    "percentageFormatted": "0%"
  },
  {
    "folder": "layers-dynamicdatalayer-table-join",
    "title": "MapImageLayer - dynamic data layer with table join",
    "matches": true,
    "matchesCriteria": "distance < 0.15 || diff.percent < 0.15",
    "distance": 0,
    "percentage": 0,
    "percentageFormatted": "0%"
  },
  {
    "folder": "layers-featurelayer",
    "title": "Intro to FeatureLayer",
    "matches": true,
    "matchesCriteria": "distance < 0.15 || diff.percent < 0.15",
    "distance": 0,
    "percentage": 0,
    "percentageFormatted": "0%"
  },
  {
    "folder": "layers-featurelayer-collection",
    "title": "Create a FeatureLayer with client-side graphics",
    "matches": true,
    "matchesCriteria": "distance < 0.15 || diff.percent < 0.15",
    "distance": 0,
    "percentage": 0,
    "percentageFormatted": "0%"
  },
  {
    "folder": "layers-featurelayer-collection-edits",
    "title": "Add or remove graphics from a FeatureLayer",
    "matches": true,
    "matchesCriteria": "distance < 0.15 || diff.percent < 0.15",
    "distance": 0,
    "percentage": 0,
    "percentageFormatted": "0%"
  },
  {
    "folder": "layers-featurelayer-large-collection",
    "title": "Working with large feature collections",
    "matches": true,
    "matchesCriteria": "distance < 0.15 || diff.percent < 0.15",
    "distance": 0,
    "percentage": 0,
    "percentageFormatted": "0%"
  },
  {
    "folder": "layers-featurelayer-shapefile",
    "title": "Create a FeatureLayer from a shapefile",
    "matches": true,
    "matchesCriteria": "distance < 0.15 || diff.percent < 0.15",
    "distance": 0,
    "percentage": 0,
    "percentageFormatted": "0%"
  },
  {
    "folder": "layers-geojson-refresh",
    "title": "GeoJSONLayer with dynamic URL",
    "matches": true,
    "matchesCriteria": "distance < 0.15 || diff.percent < 0.15",
    "distance": 0,
    "percentage": 0,
    "percentageFormatted": "0%"
  },
  {
    "folder": "layers-hosted-imagerytilelayer",
    "title": "Transposed multidimensional ImageryTileLayer",
    "matches": true,
    "matchesCriteria": "distance < 0.15 || diff.percent < 0.15",
    "distance": 0,
    "percentage": 0,
    "percentageFormatted": "0%"
  },
  {
    "folder": "layers-imagery-attribute-table",
    "title": "ImageryLayer - raster attribute table",
    "matches": true,
    "matchesCriteria": "distance < 0.15 || diff.percent < 0.15",
    "distance": 0,
    "percentage": 0,
    "percentageFormatted": "0%"
  },
  {
    "folder": "layers-imagery-clientside",
    "title": "ImageryLayer - client side chart",
    "matches": true,
    "matchesCriteria": "distance < 0.15 || diff.percent < 0.15",
    "distance": 0,
    "percentage": 0,
    "percentageFormatted": "0%"
  },
  {
    "folder": "layers-imagery-coordinatesystem",
    "title": "ImageryLayer - image coordinate system",
    "matches": true,
    "matchesCriteria": "distance < 0.15 || diff.percent < 0.15",
    "distance": 0,
    "percentage": 0,
    "percentageFormatted": "0%"
  },
  {
    "folder": "layers-imagery-multidimensional",
    "title": "Multidimensional ImageryTileLayer",
    "matches": true,
    "matchesCriteria": "distance < 0.15 || diff.percent < 0.15",
    "distance": 0,
    "percentage": 0,
    "percentageFormatted": "0%"
  },
  {
    "folder": "layers-imagery-pixelvalues",
    "title": "ImageryLayer - client side pixel filter",
    "matches": true,
    "matchesCriteria": "distance < 0.15 || diff.percent < 0.15",
    "distance": 0,
    "percentage": 0,
    "percentageFormatted": "0%"
  },
  {
    "folder": "layers-imagery-renderer",
    "title": "ImageryTileLayer - shaded relief renderer",
    "matches": true,
    "matchesCriteria": "distance < 0.15 || diff.percent < 0.15",
    "distance": 0,
    "percentage": 0,
    "percentageFormatted": "0%"
  },
  {
    "folder": "layers-imagery-renderingrule",
    "title": "ImageryLayer - client side rendering rules",
    "matches": true,
    "matchesCriteria": "distance < 0.15 || diff.percent < 0.15",
    "distance": 0,
    "percentage": 0,
    "percentageFormatted": "0%"
  },
  {
    "folder": "layers-imagery-vfrenderer",
    "title": "Visualizing wind data with VectorFieldRenderer",
    "matches": true,
    "matchesCriteria": "distance < 0.15 || diff.percent < 0.15",
    "distance": 0,
    "percentage": 0,
    "percentageFormatted": "0%"
  },
  {
    "folder": "layers-imagerylayer",
    "title": "Intro to ImageryLayer",
    "matches": true,
    "matchesCriteria": "distance < 0.15 || diff.percent < 0.15",
    "distance": 0,
    "percentage": 0,
    "percentageFormatted": "0%"
  },
  {
    "folder": "layers-imagerytilelayer-rasterfunction",
    "title": "ImageryTileLayer - raster function",
    "matches": true,
    "matchesCriteria": "distance < 0.15 || diff.percent < 0.15",
    "distance": 0,
    "percentage": 0,
    "percentageFormatted": "0%"
  },
  {
    "folder": "layers-integratedmeshlayer",
    "title": "IntegratedMeshLayer",
    "matches": true,
    "matchesCriteria": "distance < 0.15 || diff.percent < 0.15",
    "distance": 0,
    "percentage": 0,
    "percentageFormatted": "0%"
  },
  {
    "folder": "layers-mapimagelayer-dynamic-labels",
    "title": "MapImageLayer - label sublayer features",
    "matches": true,
    "matchesCriteria": "distance < 0.15 || diff.percent < 0.15",
    "distance": 0,
    "percentage": 0,
    "percentageFormatted": "0%"
  },
  {
    "folder": "layers-mapimagelayer-renderers",
    "title": "MapImageLayer - set renderers on sublayers",
    "matches": true,
    "matchesCriteria": "distance < 0.15 || diff.percent < 0.15",
    "distance": 0,
    "percentage": 0,
    "percentageFormatted": "0%"
  },
  {
    "folder": "layers-mapimagelayer-sublayers",
    "title": "MapImageLayer - Toggle sublayer visibility",
    "matches": true,
    "matchesCriteria": "distance < 0.15 || diff.percent < 0.15",
    "distance": 0,
    "percentage": 0,
    "percentageFormatted": "0%"
  },
  {
    "folder": "layers-mapnoteslayer",
    "title": "MapNotesLayer",
    "matches": true,
    "matchesCriteria": "distance < 0.15 || diff.percent < 0.15",
    "distance": 0,
    "percentage": 0,
    "percentageFormatted": "0%"
  },
  {
    "folder": "layers-medialayer-control-points",
    "title": "MediaLayer with control points",
    "matches": true,
    "matchesCriteria": "distance < 0.15 || diff.percent < 0.15",
    "distance": 0,
    "percentage": 0,
    "percentageFormatted": "0%"
  },
  {
    "folder": "layers-streamlayer-client",
    "title": "Client-side StreamLayer",
    "matches": true,
    "matchesCriteria": "distance < 0.15 || diff.percent < 0.15",
    "distance": 0,
    "percentage": 0,
    "percentageFormatted": "0%"
  },
  {
    "folder": "layers-subtypegrouplayer",
    "title": "Intro to SubtypeGroupLayer",
    "matches": true,
    "matchesCriteria": "distance < 0.15 || diff.percent < 0.15",
    "distance": 0,
    "percentage": 0,
    "percentageFormatted": "0%"
  },
  {
    "folder": "layers-tilelayer",
    "title": "Intro to TileLayer",
    "matches": true,
    "matchesCriteria": "distance < 0.15 || diff.percent < 0.15",
    "distance": 0,
    "percentage": 0,
    "percentageFormatted": "0%"
  },
  {
    "folder": "layers-vectortilelayer",
    "title": "VectorTileLayer",
    "matches": true,
    "matchesCriteria": "distance < 0.15 || diff.percent < 0.15",
    "distance": 0,
    "percentage": 0,
    "percentageFormatted": "0%"
  },
  {
    "folder": "layers-voxel-color-stops",
    "title": "VoxelLayer Color Stops",
    "matches": true,
    "matchesCriteria": "distance < 0.15 || diff.percent < 0.15",
    "distance": 0,
    "percentage": 0,
    "percentageFormatted": "0%"
  },
  {
    "folder": "layers-voxel-discrete-variable",
    "title": "VoxelLayer Discrete Variable",
    "matches": true,
    "matchesCriteria": "distance < 0.15 || diff.percent < 0.15",
    "distance": 0,
    "percentage": 0,
    "percentageFormatted": "0%"
  },
  {
    "folder": "layers-voxel-dynamic-sections",
    "title": "VoxelLayer Dynamic Sections",
    "matches": true,
    "matchesCriteria": "distance < 0.15 || diff.percent < 0.15",
    "distance": 0,
    "percentage": 0,
    "percentageFormatted": "0%"
  },
  {
    "folder": "layers-voxel-isosurface",
    "title": "VoxelLayer Isosurface",
    "matches": true,
    "matchesCriteria": "distance < 0.15 || diff.percent < 0.15",
    "distance": 0,
    "percentage": 0,
    "percentageFormatted": "0%"
  },
  {
    "folder": "layers-voxel-opacity-stops",
    "title": "VoxelLayer Opacity Stops",
    "matches": true,
    "matchesCriteria": "distance < 0.15 || diff.percent < 0.15",
    "distance": 0,
    "percentage": 0,
    "percentageFormatted": "0%"
  },
  {
    "folder": "layers-voxel-slices",
    "title": "Create area of interest for VoxelLayer",
    "matches": true,
    "matchesCriteria": "distance < 0.15 || diff.percent < 0.15",
    "distance": 0,
    "percentage": 0,
    "percentageFormatted": "0%"
  },
  {
    "folder": "layers-wcslayer",
    "title": "Intro to WCSLayer",
    "matches": true,
    "matchesCriteria": "distance < 0.15 || diff.percent < 0.15",
    "distance": 0,
    "percentage": 0,
    "percentageFormatted": "0%"
  },
  {
    "folder": "layers-wfs",
    "title": "WFSLayer",
    "matches": true,
    "matchesCriteria": "distance < 0.15 || diff.percent < 0.15",
    "distance": 0,
    "percentage": 0,
    "percentageFormatted": "0%"
  },
  {
    "folder": "layers-wmts",
    "title": "WMTSLayer",
    "matches": true,
    "matchesCriteria": "distance < 0.15 || diff.percent < 0.15",
    "distance": 0,
    "percentage": 0,
    "percentageFormatted": "0%"
  },
  {
    "folder": "layers-wmts-sublayers",
    "title": "Select WMTSLayer sublayer",
    "matches": true,
    "matchesCriteria": "distance < 0.15 || diff.percent < 0.15",
    "distance": 0,
    "percentage": 0,
    "percentageFormatted": "0%"
  },
  {
    "folder": "playground",
    "title": "Symbol playground",
    "matches": true,
    "matchesCriteria": "distance < 0.15 || diff.percent < 0.15",
    "distance": 0,
    "percentage": 0,
    "percentageFormatted": "0%"
  },
  {
    "folder": "popup-actions",
    "title": "Popup actions",
    "matches": true,
    "matchesCriteria": "distance < 0.15 || diff.percent < 0.15",
    "distance": 0,
    "percentage": 0,
    "percentageFormatted": "0%"
  },
  {
    "folder": "popup-customcontent",
    "title": "Custom popup content",
    "matches": true,
    "matchesCriteria": "distance < 0.15 || diff.percent < 0.15",
    "distance": 0,
    "percentage": 0,
    "percentageFormatted": "0%"
  },
  {
    "folder": "popup-docking-position",
    "title": "Popup dock positions",
    "matches": true,
    "matchesCriteria": "distance < 0.15 || diff.percent < 0.15",
    "distance": 0,
    "percentage": 0,
    "percentageFormatted": "0%"
  },
  {
    "folder": "popuptemplate-arcade",
    "title": "Reference Arcade expressions in PopupTemplate",
    "matches": true,
    "matchesCriteria": "distance < 0.15 || diff.percent < 0.15",
    "distance": 0,
    "percentage": 0,
    "percentageFormatted": "0%"
  },
  {
    "folder": "popuptemplate-function",
    "title": "PopupTemplate - use functions to set content",
    "matches": true,
    "matchesCriteria": "distance < 0.15 || diff.percent < 0.15",
    "distance": 0,
    "percentage": 0,
    "percentageFormatted": "0%"
  },
  {
    "folder": "popuptemplate-promise",
    "title": "PopupTemplate with promise",
    "matches": true,
    "matchesCriteria": "distance < 0.15 || diff.percent < 0.15",
    "distance": 0,
    "percentage": 0,
    "percentageFormatted": "0%"
  },
  {
    "folder": "portalitem-dragndrop",
    "title": "Load portal items via drag & drop",
    "matches": true,
    "matchesCriteria": "distance < 0.15 || diff.percent < 0.15",
    "distance": 0,
    "percentage": 0,
    "percentageFormatted": "0%"
  },
  {
    "folder": "query-attachments",
    "title": "Query Attachments",
    "matches": true,
    "matchesCriteria": "distance < 0.15 || diff.percent < 0.15",
    "distance": 0,
    "percentage": 0,
    "percentageFormatted": "0%"
  },
  {
    "folder": "query-related-features",
    "title": "Query Related Features",
    "matches": true,
    "matchesCriteria": "distance < 0.15 || diff.percent < 0.15",
    "distance": 0,
    "percentage": 0,
    "percentageFormatted": "0%"
  },
  {
    "folder": "request",
    "title": "Request data from a remote server",
    "matches": true,
    "matchesCriteria": "distance < 0.15 || diff.percent < 0.15",
    "distance": 0,
    "percentage": 0,
    "percentageFormatted": "0%"
  },
  {
    "folder": "sketch-snapping-magnifier",
    "title": "Snapping with Sketch widget and Magnifier",
    "matches": true,
    "matchesCriteria": "distance < 0.15 || diff.percent < 0.15",
    "distance": 0,
    "percentage": 0,
    "percentageFormatted": "0%"
  },
  {
    "folder": "styling-icon-fonts",
    "title": "Using Esri Icon Fonts with map graphics",
    "matches": true,
    "matchesCriteria": "distance < 0.15 || diff.percent < 0.15",
    "distance": 0,
    "percentage": 0,
    "percentageFormatted": "0%"
  },
  {
    "folder": "styling-simple-theme",
    "title": "Simple theme",
    "matches": true,
    "matchesCriteria": "distance < 0.15 || diff.percent < 0.15",
    "distance": 0,
    "percentage": 0,
    "percentageFormatted": "0%"
  },
  {
    "folder": "styling-themes",
    "title": "Themes",
    "matches": true,
    "matchesCriteria": "distance < 0.15 || diff.percent < 0.15",
    "distance": 0,
    "percentage": 0,
    "percentageFormatted": "0%"
  },
  {
    "folder": "timeslider-filter",
    "title": "Filter features with TimeSlider",
    "matches": true,
    "matchesCriteria": "distance < 0.15 || diff.percent < 0.15",
    "distance": 0,
    "percentage": 0,
    "percentageFormatted": "0%"
  },
  {
    "folder": "view-disable-navigation",
    "title": "Disable all view navigation",
    "matches": true,
    "matchesCriteria": "distance < 0.15 || diff.percent < 0.15",
    "distance": 0,
    "percentage": 0,
    "percentageFormatted": "0%"
  },
  {
    "folder": "view-disable-rotation",
    "title": "Disable rotation on the view",
    "matches": true,
    "matchesCriteria": "distance < 0.15 || diff.percent < 0.15",
    "distance": 0,
    "percentage": 0,
    "percentageFormatted": "0%"
  },
  {
    "folder": "view-hittest",
    "title": "Access features with pointer events",
    "matches": true,
    "matchesCriteria": "distance < 0.15 || diff.percent < 0.15",
    "distance": 0,
    "percentage": 0,
    "percentageFormatted": "0%"
  },
  {
    "folder": "view-padding",
    "title": "View padding",
    "matches": true,
    "matchesCriteria": "distance < 0.15 || diff.percent < 0.15",
    "distance": 0,
    "percentage": 0,
    "percentageFormatted": "0%"
  },
  {
    "folder": "views-composite-views",
    "title": "Create an app with composite views",
    "matches": true,
    "matchesCriteria": "distance < 0.15 || diff.percent < 0.15",
    "distance": 0,
    "percentage": 0,
    "percentageFormatted": "0%"
  },
  {
    "folder": "views-switch-2d-3d",
    "title": "Switch view from 2D to 3D",
    "matches": true,
    "matchesCriteria": "distance < 0.15 || diff.percent < 0.15",
    "distance": 0,
    "percentage": 0,
    "percentageFormatted": "0%"
  },
  {
    "folder": "visualization-arcade",
    "title": "Create a custom visualization using Arcade",
    "matches": true,
    "matchesCriteria": "distance < 0.15 || diff.percent < 0.15",
    "distance": 0,
    "percentage": 0,
    "percentageFormatted": "0%"
  },
  {
    "folder": "visualization-histogram-color",
    "title": "Customize ColorSlider Histogram",
    "matches": true,
    "matchesCriteria": "distance < 0.15 || diff.percent < 0.15",
    "distance": 0,
    "percentage": 0,
    "percentageFormatted": "0%"
  },
  {
    "folder": "visualization-location-simple",
    "title": "Visualize all features with the same symbol",
    "matches": true,
    "matchesCriteria": "distance < 0.15 || diff.percent < 0.15",
    "distance": 0,
    "percentage": 0,
    "percentageFormatted": "0%"
  },
  {
    "folder": "visualization-location-types",
    "title": "Visualize features by type",
    "matches": true,
    "matchesCriteria": "distance < 0.15 || diff.percent < 0.15",
    "distance": 0,
    "percentage": 0,
    "percentageFormatted": "0%"
  },
  {
    "folder": "visualization-pie-chart",
    "title": "Pie charts",
    "matches": true,
    "matchesCriteria": "distance < 0.15 || diff.percent < 0.15",
    "distance": 0,
    "percentage": 0,
    "percentageFormatted": "0%"
  },
  {
    "folder": "visualization-sm-color",
    "title": "Generate continuous color visualization",
    "matches": true,
    "matchesCriteria": "distance < 0.15 || diff.percent < 0.15",
    "distance": 0,
    "percentage": 0,
    "percentageFormatted": "0%"
  },
  {
    "folder": "visualization-sm-color-ramps",
    "title": "Esri Color Ramps",
    "matches": true,
    "matchesCriteria": "distance < 0.15 || diff.percent < 0.15",
    "distance": 0,
    "percentage": 0,
    "percentageFormatted": "0%"
  },
  {
    "folder": "visualization-sm-multivariate",
    "title": "Multivariate data exploration",
    "matches": true,
    "matchesCriteria": "distance < 0.15 || diff.percent < 0.15",
    "distance": 0,
    "percentage": 0,
    "percentageFormatted": "0%"
  },
  {
    "folder": "visualization-sm-predominance",
    "title": "Generate a predominance visualization",
    "matches": true,
    "matchesCriteria": "distance < 0.15 || diff.percent < 0.15",
    "distance": 0,
    "percentage": 0,
    "percentageFormatted": "0%"
  },
  {
    "folder": "visualization-sm-size",
    "title": "Generate data-driven continuous size visualization",
    "matches": true,
    "matchesCriteria": "distance < 0.15 || diff.percent < 0.15",
    "distance": 0,
    "percentage": 0,
    "percentageFormatted": "0%"
  },
  {
    "folder": "visualization-sm-size-themes",
    "title": "Size visual variable themes",
    "matches": true,
    "matchesCriteria": "distance < 0.15 || diff.percent < 0.15",
    "distance": 0,
    "percentage": 0,
    "percentageFormatted": "0%"
  },
  {
    "folder": "visualization-sm-sublayer",
    "title": "MapImageLayer - Explore data from a dynamic workspace",
    "matches": true,
    "matchesCriteria": "distance < 0.15 || diff.percent < 0.15",
    "distance": 0,
    "percentage": 0,
    "percentageFormatted": "0%"
  },
  {
    "folder": "visualization-sm-types",
    "title": "Generate data-driven visualization of unique values",
    "matches": true,
    "matchesCriteria": "distance < 0.15 || diff.percent < 0.15",
    "distance": 0,
    "percentage": 0,
    "percentageFormatted": "0%"
  },
  {
    "folder": "visualization-unique-value-order",
    "title": "Sort features by legend order",
    "matches": true,
    "matchesCriteria": "distance < 0.15 || diff.percent < 0.15",
    "distance": 0,
    "percentage": 0,
    "percentageFormatted": "0%"
  },
  {
    "folder": "visualization-vv-color",
    "title": "Data-driven continuous color",
    "matches": true,
    "matchesCriteria": "distance < 0.15 || diff.percent < 0.15",
    "distance": 0,
    "percentage": 0,
    "percentageFormatted": "0%"
  },
  {
    "folder": "visualization-vv-rotation",
    "title": "Visualize data with rotation",
    "matches": true,
    "matchesCriteria": "distance < 0.15 || diff.percent < 0.15",
    "distance": 0,
    "percentage": 0,
    "percentageFormatted": "0%"
  },
  {
    "folder": "visualization-vv-size",
    "title": "Data-driven continuous size",
    "matches": true,
    "matchesCriteria": "distance < 0.15 || diff.percent < 0.15",
    "distance": 0,
    "percentage": 0,
    "percentageFormatted": "0%"
  },
  {
    "folder": "webmap-basic",
    "title": "Load a basic WebMap",
    "matches": true,
    "matchesCriteria": "distance < 0.15 || diff.percent < 0.15",
    "distance": 0,
    "percentage": 0,
    "percentageFormatted": "0%"
  },
  {
    "folder": "webmap-save",
    "title": "Save a web map",
    "matches": true,
    "matchesCriteria": "distance < 0.15 || diff.percent < 0.15",
    "distance": 0,
    "percentage": 0,
    "percentageFormatted": "0%"
  },
  {
    "folder": "webmap-swap",
    "title": "Swap web maps in the same view",
    "matches": true,
    "matchesCriteria": "distance < 0.15 || diff.percent < 0.15",
    "distance": 0,
    "percentage": 0,
    "percentageFormatted": "0%"
  },
  {
    "folder": "widgets-bookmarks",
    "title": "Bookmarks widget",
    "matches": true,
    "matchesCriteria": "distance < 0.15 || diff.percent < 0.15",
    "distance": 0,
    "percentage": 0,
    "percentageFormatted": "0%"
  },
  {
    "folder": "widgets-coordinateconversion",
    "title": "CoordinateConversion widget",
    "matches": true,
    "matchesCriteria": "distance < 0.15 || diff.percent < 0.15",
    "distance": 0,
    "percentage": 0,
    "percentageFormatted": "0%"
  },
  {
    "folder": "widgets-feature-sidepanel",
    "title": "Feature widget in a side panel",
    "matches": true,
    "matchesCriteria": "distance < 0.15 || diff.percent < 0.15",
    "distance": 0,
    "percentage": 0,
    "percentageFormatted": "0%"
  },
  {
    "folder": "widgets-featuretable",
    "title": "FeatureTable",
    "matches": true,
    "matchesCriteria": "distance < 0.15 || diff.percent < 0.15",
    "distance": 0,
    "percentage": 0,
    "percentageFormatted": "0%"
  },
  {
    "folder": "widgets-featuretable-popup-interaction",
    "title": "FeatureTable with popup interaction",
    "matches": true,
    "matchesCriteria": "distance < 0.15 || diff.percent < 0.15",
    "distance": 0,
    "percentage": 0,
    "percentageFormatted": "0%"
  },
  {
    "folder": "widgets-histogram",
    "title": "Histogram widget",
    "matches": true,
    "matchesCriteria": "distance < 0.15 || diff.percent < 0.15",
    "distance": 0,
    "percentage": 0,
    "percentageFormatted": "0%"
  },
  {
    "folder": "widgets-layerlist-actions",
    "title": "LayerList widget with actions",
    "matches": true,
    "matchesCriteria": "distance < 0.15 || diff.percent < 0.15",
    "distance": 0,
    "percentage": 0,
    "percentageFormatted": "0%"
  },
  {
    "folder": "widgets-layerlist-legend",
    "title": "Add a Legend to LayerList",
    "matches": true,
    "matchesCriteria": "distance < 0.15 || diff.percent < 0.15",
    "distance": 0,
    "percentage": 0,
    "percentageFormatted": "0%"
  },
  {
    "folder": "widgets-legend-card",
    "title": "Legend widget card style",
    "matches": true,
    "matchesCriteria": "distance < 0.15 || diff.percent < 0.15",
    "distance": 0,
    "percentage": 0,
    "percentageFormatted": "0%"
  },
  {
    "folder": "widgets-locate",
    "title": "Locate button",
    "matches": true,
    "matchesCriteria": "distance < 0.15 || diff.percent < 0.15",
    "distance": 0,
    "percentage": 0,
    "percentageFormatted": "0%"
  },
  {
    "folder": "widgets-measurement",
    "title": "Measurement widget",
    "matches": true,
    "matchesCriteria": "distance < 0.15 || diff.percent < 0.15",
    "distance": 0,
    "percentage": 0,
    "percentageFormatted": "0%"
  },
  {
    "folder": "widgets-measurement-2d",
    "title": "Measurement in 2D",
    "matches": true,
    "matchesCriteria": "distance < 0.15 || diff.percent < 0.15",
    "distance": 0,
    "percentage": 0,
    "percentageFormatted": "0%"
  },
  {
    "folder": "widgets-print",
    "title": "Print widget",
    "matches": true,
    "matchesCriteria": "distance < 0.15 || diff.percent < 0.15",
    "distance": 0,
    "percentage": 0,
    "percentageFormatted": "0%"
  },
  {
    "folder": "widgets-scalebar",
    "title": "ScaleBar widget",
    "matches": true,
    "matchesCriteria": "distance < 0.15 || diff.percent < 0.15",
    "distance": 0,
    "percentage": 0,
    "percentageFormatted": "0%"
  },
  {
    "folder": "widgets-search-multiplesource",
    "title": "Search widget with multiple sources",
    "matches": true,
    "matchesCriteria": "distance < 0.15 || diff.percent < 0.15",
    "distance": 0,
    "percentage": 0,
    "percentageFormatted": "0%"
  },
  {
    "folder": "widgets-swipe",
    "title": "Swipe Widget",
    "matches": true,
    "matchesCriteria": "distance < 0.15 || diff.percent < 0.15",
    "distance": 0,
    "percentage": 0,
    "percentageFormatted": "0%"
  },
  {
    "folder": "widgets-tablelist",
    "title": "TableList widget",
    "matches": true,
    "matchesCriteria": "distance < 0.15 || diff.percent < 0.15",
    "distance": 0,
    "percentage": 0,
    "percentageFormatted": "0%"
  },
  {
    "folder": "widgets-timeslider-offset",
    "title": "TimeSlider with timeOffset and actions",
    "matches": true,
    "matchesCriteria": "distance < 0.15 || diff.percent < 0.15",
    "distance": 0,
    "percentage": 0,
    "percentageFormatted": "0%"
  }
]
